[
  {
    "Date": "2025-11-10",
    "Volume": 32911,
    "Close": 3939.92,
    "Change": -0.03,
    "Change%": "-0.00%"
  },
  {
    "Date": "2025-11-07",
    "Volume": 4237,
    "Close": 3939.95,
    "Change": -0.03,
    "Change%": "-0.00%"
  },
  {
    "Date": "2025-11-06",
    "Volume": 19659,
    "Close": 3939.98,
    "Change": -0.02,
    "Change%": "-0.00%"
  },
  {
    "Date": "2025-11-05",
    "Volume": 8705,
    "Close": 3940.0,
    "Change": 0.01,
    "Change%": "+0.00%"
  },
  {
    "Date": "2025-11-04",
    "Volume": 3333,
    "Close": 3939.99,
    "Change": NaN,
    "Change%": NaN
  },
  {
    "Date": "2025-11-03",
    "Volume": 5041,
    "Close": 3939.99,
    "Change": -0.01,
    "Change%": "-0.00%"
  },
  {
    "Date": "2025-10-31",
    "Volume": 17524,
    "Close": 3940.0,
    "Change": 0.05,
    "Change%": "+0.00%"
  },
  {
    "Date": "2025-10-30",
    "Volume": 9695,
    "Close": 3939.95,
    "Change": -0.05,
    "Change%": "-0.00%"
  },
  {
    "Date": "2025-10-29",
    "Volume": 10044,
    "Close": 3940.0,
    "Change": -0.87,
    "Change%": "-0.02%"
  },
  {
    "Date": "2025-10-28",
    "Volume": 20915,
    "Close": 3940.87,
    "Change": NaN,
    "Change%": NaN
  }
]