[
  {
    "Date": "2025-11-03",
    "Volume": 100,
    "Close": 8.75,
    "Change": 0.951951,
    "Change%": "+12.21%"
  },
  {
    "Date": "2025-10-30",
    "Volume": 65600,
    "Close": 7.798049,
    "Change": 0.296799,
    "Change%": "+3.96%"
  },
  {
    "Date": "2025-10-29",
    "Volume": 1600,
    "Close": 7.50125,
    "Change": 0.07125,
    "Change%": "+0.96%"
  },
  {
    "Date": "2025-10-28",
    "Volume": 1200,
    "Close": 7.43,
    "Change": 0.1,
    "Change%": "+1.36%"
  },
  {
    "Date": "2025-10-27",
    "Volume": 100,
    "Close": 7.33,
    "Change": 0.007737,
    "Change%": "+0.11%"
  },
  {
    "Date": "2025-10-23",
    "Volume": 35800,
    "Close": 7.322263,
    "Change": 0.067263,
    "Change%": "+0.93%"
  },
  {
    "Date": "2025-10-22",
    "Volume": 2800,
    "Close": 7.255,
    "Change": -0.1985,
    "Change%": "-2.66%"
  },
  {
    "Date": "2025-10-21",
    "Volume": 2600,
    "Close": 7.4535,
    "Change": 0.2498,
    "Change%": "+3.47%"
  },
  {
    "Date": "2025-10-17",
    "Volume": 85800,
    "Close": 7.2037,
    "Change": 0.003579,
    "Change%": "+0.05%"
  },
  {
    "Date": "2025-10-16",
    "Volume": 9055500,
    "Close": 7.200121,
    "Change": NaN,
    "Change%": NaN
  }
]