[
  {
    "Date": "2015-11-03",
    "Price": 0.000880449
  },
  {
    "Date": "2015-11-04",
    "Price": 0.000877048
  },
  {
    "Date": "2015-11-05",
    "Price": 0.000880449
  },
  {
    "Date": "2015-11-06",
    "Price": 0.000864441
  },
  {
    "Date": "2015-11-09",
    "Price": 0.000864441
  },
  {
    "Date": "2015-11-10",
    "Price": 0.000864441
  },
  {
    "Date": "2015-11-11",
    "Price": 0.000867443
  },
  {
    "Date": "2015-11-12",
    "Price": 0.000867443
  },
  {
    "Date": "2015-11-13",
    "Price": 0.000867443
  },
  {
    "Date": "2015-11-16",
    "Price": 0.000867443
  },
  {
    "Date": "2015-11-17",
    "Price": 0.000867443
  },
  {
    "Date": "2015-11-18",
    "Price": 0.000867443
  },
  {
    "Date": "2015-11-19",
    "Price": 0.000867443
  },
  {
    "Date": "2015-11-20",
    "Price": 0.000866002
  },
  {
    "Date": "2015-11-23",
    "Price": 0.000866002
  },
  {
    "Date": "2015-11-24",
    "Price": 0.000856437
  },
  {
    "Date": "2015-11-25",
    "Price": 0.000856437
  },
  {
    "Date": "2015-11-26",
    "Price": 0.000856437
  },
  {
    "Date": "2015-11-27",
    "Price": 0.000844791
  },
  {
    "Date": "2015-11-30",
    "Price": 0.000844431
  },
  {
    "Date": "2015-12-01",
    "Price": 0.000846432
  },
  {
    "Date": "2015-12-02",
    "Price": 0.000846912
  },
  {
    "Date": "2015-12-03",
    "Price": 0.000844431
  },
  {
    "Date": "2015-12-04",
    "Price": 0.000841429
  },
  {
    "Date": "2015-12-07",
    "Price": 0.000840429
  },
  {
    "Date": "2015-12-08",
    "Price": 0.00084243
  },
  {
    "Date": "2015-12-09",
    "Price": 0.000833065
  },
  {
    "Date": "2015-12-10",
    "Price": 0.000820539
  },
  {
    "Date": "2015-12-11",
    "Price": 0.000820419
  },
  {
    "Date": "2015-12-14",
    "Price": 0.000820419
  },
  {
    "Date": "2015-12-15",
    "Price": 0.000816417
  },
  {
    "Date": "2015-12-16",
    "Price": 0.000816417
  },
  {
    "Date": "2015-12-17",
    "Price": 0.000816417
  },
  {
    "Date": "2015-12-18",
    "Price": 0.000816417
  },
  {
    "Date": "2015-12-21",
    "Price": 0.000816417
  },
  {
    "Date": "2015-12-23",
    "Price": 0.000816417
  },
  {
    "Date": "2015-12-24",
    "Price": 0.000812975
  },
  {
    "Date": "2015-12-28",
    "Price": 0.000812975
  },
  {
    "Date": "2015-12-29",
    "Price": 0.000815416
  },
  {
    "Date": "2015-12-30",
    "Price": 0.000815416
  },
  {
    "Date": "2015-12-31",
    "Price": 0.000814055
  },
  {
    "Date": "2016-01-04",
    "Price": 0.000808853
  },
  {
    "Date": "2016-01-05",
    "Price": 0.000808853
  },
  {
    "Date": "2016-01-06",
    "Price": 0.000792404
  },
  {
    "Date": "2016-01-07",
    "Price": 0.000792404
  },
  {
    "Date": "2016-01-08",
    "Price": 0.000792404
  },
  {
    "Date": "2016-01-11",
    "Price": 0.000792404
  },
  {
    "Date": "2016-01-12",
    "Price": 0.000792404
  },
  {
    "Date": "2016-01-13",
    "Price": 0.000792404
  },
  {
    "Date": "2016-01-14",
    "Price": 0.000776396
  },
  {
    "Date": "2016-01-15",
    "Price": 0.000776396
  },
  {
    "Date": "2016-01-18",
    "Price": 0.000766391
  },
  {
    "Date": "2016-01-19",
    "Price": 0.000766391
  },
  {
    "Date": "2016-01-20",
    "Price": 0.000752384
  },
  {
    "Date": "2016-01-21",
    "Price": 0.000723649
  },
  {
    "Date": "2016-01-22",
    "Price": 0.000723649
  },
  {
    "Date": "2016-01-25",
    "Price": 0.000723649
  },
  {
    "Date": "2016-01-26",
    "Price": 0.000680347
  },
  {
    "Date": "2016-01-27",
    "Price": 0.000680347
  },
  {
    "Date": "2016-01-28",
    "Price": 0.000680347
  },
  {
    "Date": "2016-01-29",
    "Price": 0.000680307
  },
  {
    "Date": "2016-02-01",
    "Price": 0.000680307
  },
  {
    "Date": "2016-02-02",
    "Price": 0.000680307
  },
  {
    "Date": "2016-02-03",
    "Price": 0.000668341
  },
  {
    "Date": "2016-02-04",
    "Price": 0.000668341
  },
  {
    "Date": "2016-02-05",
    "Price": 0.000707841
  },
  {
    "Date": "2016-02-08",
    "Price": 0.000715685
  },
  {
    "Date": "2016-02-09",
    "Price": 0.000712684
  },
  {
    "Date": "2016-02-10",
    "Price": 0.000719967
  },
  {
    "Date": "2016-02-11",
    "Price": 0.000720368
  },
  {
    "Date": "2016-02-12",
    "Price": 0.000720368
  },
  {
    "Date": "2016-02-15",
    "Price": 0.000720368
  },
  {
    "Date": "2016-02-16",
    "Price": 0.000721328
  },
  {
    "Date": "2016-02-17",
    "Price": 0.000720448
  },
  {
    "Date": "2016-02-18",
    "Price": 0.000720448
  },
  {
    "Date": "2016-02-19",
    "Price": 0.000720448
  },
  {
    "Date": "2016-02-22",
    "Price": 0.000720368
  },
  {
    "Date": "2016-02-23",
    "Price": 0.000720368
  },
  {
    "Date": "2016-02-24",
    "Price": 0.000720368
  },
  {
    "Date": "2016-02-25",
    "Price": 0.000720368
  },
  {
    "Date": "2016-02-26",
    "Price": 0.000720368
  },
  {
    "Date": "2016-02-29",
    "Price": 0.000720368
  },
  {
    "Date": "2016-03-01",
    "Price": 0.000720368
  },
  {
    "Date": "2016-03-02",
    "Price": 0.000720368
  },
  {
    "Date": "2016-03-03",
    "Price": 0.000720368
  },
  {
    "Date": "2016-03-04",
    "Price": 0.000721568
  },
  {
    "Date": "2016-03-07",
    "Price": 0.00072437
  },
  {
    "Date": "2016-03-08",
    "Price": 0.00072437
  },
  {
    "Date": "2016-03-09",
    "Price": 0.00072437
  },
  {
    "Date": "2016-03-10",
    "Price": 0.000726371
  },
  {
    "Date": "2016-03-11",
    "Price": 0.000728372
  },
  {
    "Date": "2016-03-14",
    "Price": 0.000760388
  },
  {
    "Date": "2016-03-15",
    "Price": 0.000788282
  },
  {
    "Date": "2016-03-16",
    "Price": 0.000825581
  },
  {
    "Date": "2016-03-17",
    "Price": 0.000825581
  },
  {
    "Date": "2016-03-18",
    "Price": 0.000825781
  },
  {
    "Date": "2016-03-21",
    "Price": 0.000825781
  },
  {
    "Date": "2016-03-22",
    "Price": 0.000832705
  },
  {
    "Date": "2016-03-23",
    "Price": 0.000832425
  },
  {
    "Date": "2016-03-24",
    "Price": 0.000832425
  },
  {
    "Date": "2016-03-29",
    "Price": 0.000840429
  },
  {
    "Date": "2016-03-30",
    "Price": 0.000868963
  },
  {
    "Date": "2016-03-31",
    "Price": 0.00088145
  },
  {
    "Date": "2016-04-01",
    "Price": 0.00088145
  },
  {
    "Date": "2016-04-04",
    "Price": 0.000880449
  },
  {
    "Date": "2016-04-05",
    "Price": 0.00088225
  },
  {
    "Date": "2016-04-06",
    "Price": 0.000885212
  },
  {
    "Date": "2016-04-07",
    "Price": 0.000884451
  },
  {
    "Date": "2016-04-08",
    "Price": 0.000885452
  },
  {
    "Date": "2016-04-11",
    "Price": 0.000887333
  },
  {
    "Date": "2016-04-12",
    "Price": 0.000887333
  },
  {
    "Date": "2016-04-13",
    "Price": 0.000890454
  },
  {
    "Date": "2016-04-14",
    "Price": 0.000892455
  },
  {
    "Date": "2016-04-15",
    "Price": 0.000894336
  },
  {
    "Date": "2016-04-19",
    "Price": 0.000894336
  },
  {
    "Date": "2016-04-20",
    "Price": 0.000894336
  },
  {
    "Date": "2016-04-21",
    "Price": 0.000895497
  },
  {
    "Date": "2016-04-22",
    "Price": 0.000898218
  },
  {
    "Date": "2016-04-25",
    "Price": 0.000898218
  },
  {
    "Date": "2016-04-26",
    "Price": 0.000898218
  },
  {
    "Date": "2016-04-27",
    "Price": 0.000898459
  },
  {
    "Date": "2016-04-28",
    "Price": 0.00088149
  },
  {
    "Date": "2016-04-29",
    "Price": 0.000880449
  },
  {
    "Date": "2016-05-03",
    "Price": 0.000880449
  },
  {
    "Date": "2016-05-04",
    "Price": 0.00088129
  },
  {
    "Date": "2016-05-05",
    "Price": 0.000880449
  },
  {
    "Date": "2016-05-06",
    "Price": 0.000879449
  },
  {
    "Date": "2016-05-09",
    "Price": 0.000879449
  },
  {
    "Date": "2016-05-10",
    "Price": 0.000878448
  },
  {
    "Date": "2016-05-11",
    "Price": 0.000878448
  },
  {
    "Date": "2016-05-12",
    "Price": 0.000878448
  },
  {
    "Date": "2016-05-13",
    "Price": 0.000880449
  },
  {
    "Date": "2016-05-16",
    "Price": 0.000876447
  },
  {
    "Date": "2016-05-17",
    "Price": 0.000876447
  },
  {
    "Date": "2016-05-18",
    "Price": 0.000876447
  },
  {
    "Date": "2016-05-19",
    "Price": 0.000876447
  },
  {
    "Date": "2016-05-20",
    "Price": 0.000876447
  },
  {
    "Date": "2016-05-23",
    "Price": 0.000875447
  },
  {
    "Date": "2016-05-24",
    "Price": 0.000873446
  },
  {
    "Date": "2016-05-26",
    "Price": 0.000873446
  },
  {
    "Date": "2016-05-27",
    "Price": 0.000888453
  },
  {
    "Date": "2016-05-30",
    "Price": 0.000885332
  },
  {
    "Date": "2016-05-31",
    "Price": 0.000885332
  },
  {
    "Date": "2016-06-01",
    "Price": 0.000885332
  },
  {
    "Date": "2016-06-02",
    "Price": 0.000890454
  },
  {
    "Date": "2016-06-03",
    "Price": 0.000894496
  },
  {
    "Date": "2016-06-06",
    "Price": 0.000896457
  },
  {
    "Date": "2016-06-07",
    "Price": 0.000897458
  },
  {
    "Date": "2016-06-08",
    "Price": 0.00090098
  },
  {
    "Date": "2016-06-09",
    "Price": 0.00090098
  },
  {
    "Date": "2016-06-10",
    "Price": 0.000907543
  },
  {
    "Date": "2016-06-13",
    "Price": 0.000907543
  },
  {
    "Date": "2016-06-14",
    "Price": 0.00092051
  },
  {
    "Date": "2016-06-15",
    "Price": 0.00092051
  },
  {
    "Date": "2016-06-16",
    "Price": 0.000925472
  },
  {
    "Date": "2016-06-17",
    "Price": 0.000925512
  },
  {
    "Date": "2016-06-20",
    "Price": 0.000914747
  },
  {
    "Date": "2016-06-21",
    "Price": 0.000914507
  },
  {
    "Date": "2016-06-22",
    "Price": 0.000914467
  },
  {
    "Date": "2016-06-23",
    "Price": 0.000914587
  },
  {
    "Date": "2016-06-24",
    "Price": 0.000914547
  },
  {
    "Date": "2016-06-27",
    "Price": 0.000914467
  },
  {
    "Date": "2016-06-28",
    "Price": 0.000914467
  },
  {
    "Date": "2016-06-29",
    "Price": 0.000914467
  },
  {
    "Date": "2016-06-30",
    "Price": 0.000914467
  },
  {
    "Date": "2016-07-01",
    "Price": 0.000914467
  },
  {
    "Date": "2016-07-04",
    "Price": 0.000915467
  },
  {
    "Date": "2016-07-05",
    "Price": 0.000915467
  },
  {
    "Date": "2016-07-06",
    "Price": 0.000915467
  },
  {
    "Date": "2016-07-07",
    "Price": 0.000915467
  },
  {
    "Date": "2016-07-08",
    "Price": 0.000916468
  },
  {
    "Date": "2016-07-11",
    "Price": 0.000914467
  },
  {
    "Date": "2016-07-12",
    "Price": 0.000914467
  },
  {
    "Date": "2016-07-13",
    "Price": 0.000915467
  },
  {
    "Date": "2016-07-14",
    "Price": 0.000917468
  },
  {
    "Date": "2016-07-15",
    "Price": 0.000917548
  },
  {
    "Date": "2016-07-18",
    "Price": 0.00092047
  },
  {
    "Date": "2016-07-19",
    "Price": 0.00092047
  },
  {
    "Date": "2016-07-20",
    "Price": 0.000925112
  },
  {
    "Date": "2016-07-21",
    "Price": 0.000925472
  },
  {
    "Date": "2016-07-22",
    "Price": 0.000925472
  },
  {
    "Date": "2016-07-25",
    "Price": 0.000925472
  },
  {
    "Date": "2016-07-26",
    "Price": 0.000925472
  },
  {
    "Date": "2016-07-27",
    "Price": 0.000925472
  },
  {
    "Date": "2016-07-28",
    "Price": 0.000926673
  },
  {
    "Date": "2016-07-29",
    "Price": 0.000929474
  },
  {
    "Date": "2016-08-01",
    "Price": 0.000929474
  },
  {
    "Date": "2016-08-02",
    "Price": 0.000930315
  },
  {
    "Date": "2016-08-03",
    "Price": 0.000933476
  },
  {
    "Date": "2016-08-04",
    "Price": 0.000933476
  },
  {
    "Date": "2016-08-05",
    "Price": 0.00093968
  },
  {
    "Date": "2016-08-10",
    "Price": 0.00093968
  },
  {
    "Date": "2016-08-11",
    "Price": 0.000943521
  },
  {
    "Date": "2016-08-12",
    "Price": 0.000970495
  },
  {
    "Date": "2016-08-15",
    "Price": 0.000970495
  },
  {
    "Date": "2016-08-16",
    "Price": 0.000965012
  },
  {
    "Date": "2016-08-17",
    "Price": 0.000966493
  },
  {
    "Date": "2016-08-18",
    "Price": 0.000989505
  },
  {
    "Date": "2016-08-19",
    "Price": 0.000992707
  },
  {
    "Date": "2016-08-22",
    "Price": 0.001000511
  },
  {
    "Date": "2016-08-23",
    "Price": 0.001003872
  },
  {
    "Date": "2016-08-24",
    "Price": 0.001017399
  },
  {
    "Date": "2016-08-25",
    "Price": 0.001023122
  },
  {
    "Date": "2016-08-26",
    "Price": 0.001025523
  },
  {
    "Date": "2016-08-29",
    "Price": 0.001026204
  },
  {
    "Date": "2016-08-30",
    "Price": 0.001028925
  },
  {
    "Date": "2016-08-31",
    "Price": 0.001033527
  },
  {
    "Date": "2016-09-01",
    "Price": 0.001035608
  },
  {
    "Date": "2016-09-02",
    "Price": 0.001060541
  },
  {
    "Date": "2016-09-05",
    "Price": 0.001068545
  },
  {
    "Date": "2016-09-06",
    "Price": 0.001070546
  },
  {
    "Date": "2016-09-07",
    "Price": 0.001074949
  },
  {
    "Date": "2016-09-08",
    "Price": 0.001079551
  },
  {
    "Date": "2016-09-09",
    "Price": 0.001079551
  },
  {
    "Date": "2016-09-12",
    "Price": 0.001079551
  },
  {
    "Date": "2016-09-13",
    "Price": 0.001080551
  },
  {
    "Date": "2016-09-14",
    "Price": 0.001080551
  },
  {
    "Date": "2016-09-15",
    "Price": 0.001080551
  },
  {
    "Date": "2016-09-16",
    "Price": 0.001081552
  },
  {
    "Date": "2016-09-19",
    "Price": 0.001082432
  },
  {
    "Date": "2016-09-20",
    "Price": 0.001084553
  },
  {
    "Date": "2016-09-21",
    "Price": 0.001090436
  },
  {
    "Date": "2016-09-22",
    "Price": 0.001091597
  },
  {
    "Date": "2016-09-23",
    "Price": 0.001091597
  },
  {
    "Date": "2016-09-26",
    "Price": 0.001091597
  },
  {
    "Date": "2016-09-27",
    "Price": 0.001094198
  },
  {
    "Date": "2016-09-28",
    "Price": 0.001094198
  },
  {
    "Date": "2016-09-29",
    "Price": 0.001118851
  },
  {
    "Date": "2016-09-30",
    "Price": 0.001160592
  },
  {
    "Date": "2016-10-03",
    "Price": 0.001160592
  },
  {
    "Date": "2016-10-04",
    "Price": 0.001199852
  },
  {
    "Date": "2016-10-05",
    "Price": 0.001200613
  },
  {
    "Date": "2016-10-06",
    "Price": 0.001200613
  },
  {
    "Date": "2016-10-07",
    "Price": 0.001200613
  },
  {
    "Date": "2016-10-10",
    "Price": 0.001220623
  },
  {
    "Date": "2016-10-11",
    "Price": 0.001222024
  },
  {
    "Date": "2016-10-12",
    "Price": 0.001236591
  },
  {
    "Date": "2016-10-13",
    "Price": 0.001240633
  },
  {
    "Date": "2016-10-14",
    "Price": 0.001260643
  },
  {
    "Date": "2016-10-17",
    "Price": 0.001261644
  },
  {
    "Date": "2016-10-18",
    "Price": 0.001261644
  },
  {
    "Date": "2016-10-19",
    "Price": 0.001263685
  },
  {
    "Date": "2016-10-20",
    "Price": 0.001280654
  },
  {
    "Date": "2016-10-21",
    "Price": 0.001265646
  },
  {
    "Date": "2016-10-24",
    "Price": 0.001265646
  },
  {
    "Date": "2016-10-25",
    "Price": 0.001265646
  },
  {
    "Date": "2016-10-26",
    "Price": 0.001265646
  },
  {
    "Date": "2016-10-27",
    "Price": 0.001280654
  },
  {
    "Date": "2016-10-28",
    "Price": 0.001288297
  },
  {
    "Date": "2016-10-31",
    "Price": 0.001288297
  },
  {
    "Date": "2016-11-01",
    "Price": 0.001288658
  },
  {
    "Date": "2016-11-02",
    "Price": 0.001288658
  },
  {
    "Date": "2016-11-03",
    "Price": 0.001288658
  },
  {
    "Date": "2016-11-04",
    "Price": 0.001288658
  },
  {
    "Date": "2016-11-07",
    "Price": 0.001288658
  },
  {
    "Date": "2016-11-08",
    "Price": 0.001288658
  },
  {
    "Date": "2016-11-09",
    "Price": 0.001288658
  },
  {
    "Date": "2016-11-10",
    "Price": 0.001288658
  },
  {
    "Date": "2016-11-14",
    "Price": 0.001288818
  },
  {
    "Date": "2016-11-15",
    "Price": 0.001288658
  },
  {
    "Date": "2016-11-16",
    "Price": 0.001288658
  },
  {
    "Date": "2016-11-17",
    "Price": 0.001288658
  },
  {
    "Date": "2016-11-18",
    "Price": 0.00129266
  },
  {
    "Date": "2016-11-21",
    "Price": 0.001320674
  },
  {
    "Date": "2016-11-22",
    "Price": 0.001321394
  },
  {
    "Date": "2016-11-23",
    "Price": 0.001320674
  },
  {
    "Date": "2016-11-24",
    "Price": 0.001334881
  },
  {
    "Date": "2016-11-25",
    "Price": 0.001355652
  },
  {
    "Date": "2016-11-28",
    "Price": 0.001355652
  },
  {
    "Date": "2016-11-29",
    "Price": 0.001355692
  },
  {
    "Date": "2016-11-30",
    "Price": 0.001358773
  },
  {
    "Date": "2016-12-01",
    "Price": 0.001361375
  },
  {
    "Date": "2016-12-02",
    "Price": 0.001361375
  },
  {
    "Date": "2016-12-05",
    "Price": 0.001361695
  },
  {
    "Date": "2016-12-06",
    "Price": 0.001362335
  },
  {
    "Date": "2016-12-07",
    "Price": 0.001378704
  },
  {
    "Date": "2016-12-08",
    "Price": 0.001385347
  },
  {
    "Date": "2016-12-09",
    "Price": 0.001385707
  },
  {
    "Date": "2016-12-12",
    "Price": 0.001387708
  },
  {
    "Date": "2016-12-13",
    "Price": 0.001392711
  },
  {
    "Date": "2016-12-14",
    "Price": 0.001392711
  },
  {
    "Date": "2016-12-15",
    "Price": 0.001396713
  },
  {
    "Date": "2016-12-16",
    "Price": 0.001397513
  },
  {
    "Date": "2016-12-19",
    "Price": 0.001397153
  },
  {
    "Date": "2016-12-20",
    "Price": 0.001400715
  },
  {
    "Date": "2016-12-21",
    "Price": 0.001400715
  },
  {
    "Date": "2016-12-23",
    "Price": 0.001396713
  },
  {
    "Date": "2016-12-28",
    "Price": 0.001396713
  },
  {
    "Date": "2016-12-29",
    "Price": 0.001397553
  },
  {
    "Date": "2016-12-30",
    "Price": 0.001397553
  },
  {
    "Date": "2017-01-03",
    "Price": 0.001398714
  },
  {
    "Date": "2017-01-04",
    "Price": 0.001398714
  },
  {
    "Date": "2017-01-05",
    "Price": 0.001398714
  },
  {
    "Date": "2017-01-06",
    "Price": 0.001399274
  },
  {
    "Date": "2017-01-09",
    "Price": 0.001399714
  },
  {
    "Date": "2017-01-10",
    "Price": 0.001399994
  },
  {
    "Date": "2017-01-11",
    "Price": 0.001400715
  },
  {
    "Date": "2017-01-12",
    "Price": 0.001400715
  },
  {
    "Date": "2017-01-13",
    "Price": 0.001400715
  },
  {
    "Date": "2017-01-16",
    "Price": 0.001400715
  },
  {
    "Date": "2017-01-17",
    "Price": 0.001400715
  },
  {
    "Date": "2017-01-18",
    "Price": 0.001401715
  },
  {
    "Date": "2017-01-19",
    "Price": 0.001402356
  },
  {
    "Date": "2017-01-20",
    "Price": 0.001402716
  },
  {
    "Date": "2017-01-23",
    "Price": 0.001402716
  },
  {
    "Date": "2017-01-24",
    "Price": 0.001405117
  },
  {
    "Date": "2017-01-25",
    "Price": 0.001405717
  },
  {
    "Date": "2017-01-26",
    "Price": 0.001404717
  },
  {
    "Date": "2017-01-27",
    "Price": 0.001404717
  },
  {
    "Date": "2017-01-30",
    "Price": 0.001404717
  },
  {
    "Date": "2017-01-31",
    "Price": 0.001403716
  },
  {
    "Date": "2017-02-01",
    "Price": 0.001400715
  },
  {
    "Date": "2017-02-02",
    "Price": 0.001400715
  },
  {
    "Date": "2017-02-03",
    "Price": 0.001400715
  },
  {
    "Date": "2017-02-06",
    "Price": 0.001400715
  },
  {
    "Date": "2017-02-07",
    "Price": 0.001400715
  },
  {
    "Date": "2017-02-08",
    "Price": 0.001400715
  },
  {
    "Date": "2017-02-09",
    "Price": 0.001400715
  },
  {
    "Date": "2017-02-10",
    "Price": 0.001400715
  },
  {
    "Date": "2017-02-13",
    "Price": 0.001400715
  },
  {
    "Date": "2017-02-14",
    "Price": 0.001400715
  },
  {
    "Date": "2017-02-15",
    "Price": 0.001400715
  },
  {
    "Date": "2017-02-16",
    "Price": 0.001400715
  },
  {
    "Date": "2017-02-17",
    "Price": 0.001400715
  },
  {
    "Date": "2017-02-20",
    "Price": 0.001400715
  },
  {
    "Date": "2017-02-21",
    "Price": 0.001400715
  },
  {
    "Date": "2017-02-22",
    "Price": 0.001400715
  },
  {
    "Date": "2017-02-23",
    "Price": 0.001400715
  },
  {
    "Date": "2017-02-24",
    "Price": 0.001380705
  },
  {
    "Date": "2017-02-27",
    "Price": 0.001380705
  },
  {
    "Date": "2017-02-28",
    "Price": 0.001379704
  },
  {
    "Date": "2017-03-01",
    "Price": 0.001378704
  },
  {
    "Date": "2017-03-02",
    "Price": 0.001384707
  },
  {
    "Date": "2017-03-03",
    "Price": 0.001384787
  },
  {
    "Date": "2017-03-06",
    "Price": 0.001385787
  },
  {
    "Date": "2017-03-07",
    "Price": 0.001386708
  },
  {
    "Date": "2017-03-08",
    "Price": 0.001388709
  },
  {
    "Date": "2017-03-09",
    "Price": 0.001388709
  },
  {
    "Date": "2017-03-10",
    "Price": 0.001388709
  },
  {
    "Date": "2017-03-13",
    "Price": 0.001389709
  },
  {
    "Date": "2017-03-14",
    "Price": 0.00139203
  },
  {
    "Date": "2017-03-15",
    "Price": 0.00139203
  },
  {
    "Date": "2017-03-16",
    "Price": 0.00139203
  },
  {
    "Date": "2017-03-17",
    "Price": 0.001402356
  },
  {
    "Date": "2017-03-20",
    "Price": 0.001402716
  },
  {
    "Date": "2017-03-21",
    "Price": 0.001402716
  },
  {
    "Date": "2017-03-22",
    "Price": 0.001404677
  },
  {
    "Date": "2017-03-23",
    "Price": 0.001406478
  },
  {
    "Date": "2017-03-24",
    "Price": 0.001406718
  },
  {
    "Date": "2017-03-27",
    "Price": 0.001408079
  },
  {
    "Date": "2017-03-28",
    "Price": 0.00141072
  },
  {
    "Date": "2017-03-29",
    "Price": 0.00141072
  },
  {
    "Date": "2017-03-30",
    "Price": 0.001414202
  },
  {
    "Date": "2017-03-31",
    "Price": 0.001425447
  },
  {
    "Date": "2017-04-03",
    "Price": 0.001428729
  },
  {
    "Date": "2017-04-04",
    "Price": 0.001428729
  },
  {
    "Date": "2017-04-05",
    "Price": 0.00142973
  },
  {
    "Date": "2017-04-06",
    "Price": 0.00143073
  },
  {
    "Date": "2017-04-07",
    "Price": 0.001433732
  },
  {
    "Date": "2017-04-10",
    "Price": 0.001433732
  },
  {
    "Date": "2017-04-11",
    "Price": 0.001440735
  },
  {
    "Date": "2017-04-12",
    "Price": 0.001442736
  },
  {
    "Date": "2017-04-13",
    "Price": 0.001442736
  },
  {
    "Date": "2017-04-19",
    "Price": 0.001442736
  },
  {
    "Date": "2017-04-20",
    "Price": 0.001444537
  },
  {
    "Date": "2017-04-21",
    "Price": 0.00145054
  },
  {
    "Date": "2017-04-24",
    "Price": 0.001452741
  },
  {
    "Date": "2017-04-25",
    "Price": 0.001452821
  },
  {
    "Date": "2017-04-26",
    "Price": 0.001456743
  },
  {
    "Date": "2017-04-27",
    "Price": 0.001459785
  },
  {
    "Date": "2017-04-28",
    "Price": 0.001459785
  },
  {
    "Date": "2017-05-02",
    "Price": 0.00146875
  },
  {
    "Date": "2017-05-03",
    "Price": 0.00146983
  },
  {
    "Date": "2017-05-04",
    "Price": 0.001476754
  },
  {
    "Date": "2017-05-05",
    "Price": 0.001481756
  },
  {
    "Date": "2017-05-08",
    "Price": 0.001501246
  },
  {
    "Date": "2017-05-09",
    "Price": 0.001500766
  },
  {
    "Date": "2017-05-10",
    "Price": 0.001500766
  },
  {
    "Date": "2017-05-11",
    "Price": 0.001500766
  },
  {
    "Date": "2017-05-12",
    "Price": 0.001500766
  },
  {
    "Date": "2017-05-15",
    "Price": 0.001500766
  },
  {
    "Date": "2017-05-16",
    "Price": 0.001502487
  },
  {
    "Date": "2017-05-17",
    "Price": 0.001475993
  },
  {
    "Date": "2017-05-18",
    "Price": 0.001500766
  },
  {
    "Date": "2017-05-19",
    "Price": 0.001501766
  },
  {
    "Date": "2017-05-22",
    "Price": 0.001501766
  },
  {
    "Date": "2017-05-23",
    "Price": 0.001501766
  },
  {
    "Date": "2017-05-24",
    "Price": 0.001504768
  },
  {
    "Date": "2017-05-26",
    "Price": 0.001505768
  },
  {
    "Date": "2017-05-29",
    "Price": 0.00150877
  },
  {
    "Date": "2017-05-30",
    "Price": 0.00150877
  },
  {
    "Date": "2017-05-31",
    "Price": 0.00150877
  },
  {
    "Date": "2017-06-01",
    "Price": 0.00150877
  },
  {
    "Date": "2017-06-02",
    "Price": 0.00150877
  },
  {
    "Date": "2017-06-05",
    "Price": 0.00150877
  },
  {
    "Date": "2017-06-06",
    "Price": 0.001510491
  },
  {
    "Date": "2017-06-07",
    "Price": 0.001510491
  },
  {
    "Date": "2017-06-08",
    "Price": 0.001511171
  },
  {
    "Date": "2017-06-09",
    "Price": 0.001517094
  },
  {
    "Date": "2017-06-12",
    "Price": 0.001521777
  },
  {
    "Date": "2017-06-13",
    "Price": 0.001526259
  },
  {
    "Date": "2017-06-14",
    "Price": 0.001526779
  },
  {
    "Date": "2017-06-15",
    "Price": 0.00152934
  },
  {
    "Date": "2017-06-16",
    "Price": 0.001531782
  },
  {
    "Date": "2017-06-19",
    "Price": 0.001532782
  },
  {
    "Date": "2017-06-20",
    "Price": 0.001532782
  },
  {
    "Date": "2017-06-21",
    "Price": 0.001540786
  },
  {
    "Date": "2017-06-22",
    "Price": 0.001540786
  },
  {
    "Date": "2017-06-23",
    "Price": 0.001540786
  },
  {
    "Date": "2017-06-26",
    "Price": 0.001540786
  },
  {
    "Date": "2017-06-27",
    "Price": 0.001541387
  },
  {
    "Date": "2017-06-28",
    "Price": 0.00154879
  },
  {
    "Date": "2017-06-29",
    "Price": 0.00154879
  },
  {
    "Date": "2017-06-30",
    "Price": 0.00154879
  },
  {
    "Date": "2017-07-03",
    "Price": 0.001549791
  },
  {
    "Date": "2017-07-04",
    "Price": 0.001568801
  },
  {
    "Date": "2017-07-05",
    "Price": 0.001568801
  },
  {
    "Date": "2017-07-06",
    "Price": 0.001568801
  },
  {
    "Date": "2017-07-07",
    "Price": 0.001572803
  },
  {
    "Date": "2017-07-10",
    "Price": 0.001572803
  },
  {
    "Date": "2017-07-11",
    "Price": 0.001572683
  },
  {
    "Date": "2017-07-12",
    "Price": 0.001572803
  },
  {
    "Date": "2017-07-13",
    "Price": 0.001572803
  },
  {
    "Date": "2017-07-14",
    "Price": 0.001572803
  },
  {
    "Date": "2017-07-17",
    "Price": 0.001572803
  },
  {
    "Date": "2017-07-18",
    "Price": 0.001572803
  },
  {
    "Date": "2017-07-19",
    "Price": 0.001571722
  },
  {
    "Date": "2017-07-20",
    "Price": 0.001572643
  },
  {
    "Date": "2017-07-21",
    "Price": 0.001572803
  },
  {
    "Date": "2017-07-24",
    "Price": 0.001572803
  },
  {
    "Date": "2017-07-25",
    "Price": 0.001572803
  },
  {
    "Date": "2017-07-26",
    "Price": 0.001572563
  },
  {
    "Date": "2017-07-27",
    "Price": 0.001572803
  },
  {
    "Date": "2017-07-28",
    "Price": 0.001572803
  },
  {
    "Date": "2017-07-31",
    "Price": 0.001572803
  },
  {
    "Date": "2017-08-01",
    "Price": 0.001573803
  },
  {
    "Date": "2017-08-02",
    "Price": 0.001574804
  },
  {
    "Date": "2017-08-03",
    "Price": 0.001575964
  },
  {
    "Date": "2017-08-04",
    "Price": 0.001575964
  },
  {
    "Date": "2017-08-07",
    "Price": 0.001576805
  },
  {
    "Date": "2017-08-08",
    "Price": 0.001576805
  },
  {
    "Date": "2017-08-09",
    "Price": 0.001576805
  },
  {
    "Date": "2017-08-10",
    "Price": 0.001576805
  },
  {
    "Date": "2017-08-11",
    "Price": 0.001576805
  },
  {
    "Date": "2017-08-16",
    "Price": 0.001576805
  },
  {
    "Date": "2017-08-17",
    "Price": 0.001577805
  },
  {
    "Date": "2017-08-18",
    "Price": 0.001581807
  },
  {
    "Date": "2017-08-21",
    "Price": 0.00160714
  },
  {
    "Date": "2017-08-22",
    "Price": 0.0016061
  },
  {
    "Date": "2017-08-23",
    "Price": 0.001612103
  },
  {
    "Date": "2017-08-24",
    "Price": 0.001612103
  },
  {
    "Date": "2017-08-25",
    "Price": 0.001616825
  },
  {
    "Date": "2017-08-28",
    "Price": 0.001621187
  },
  {
    "Date": "2017-08-29",
    "Price": 0.001621187
  },
  {
    "Date": "2017-08-30",
    "Price": 0.001636875
  },
  {
    "Date": "2017-08-31",
    "Price": 0.00164584
  },
  {
    "Date": "2017-09-01",
    "Price": 0.001708872
  },
  {
    "Date": "2017-09-04",
    "Price": 0.001729403
  },
  {
    "Date": "2017-09-05",
    "Price": 0.001838298
  },
  {
    "Date": "2017-09-06",
    "Price": 0.001884602
  },
  {
    "Date": "2017-09-07",
    "Price": 0.001905973
  },
  {
    "Date": "2017-09-08",
    "Price": 0.001963842
  },
  {
    "Date": "2017-09-11",
    "Price": 0.002001021
  },
  {
    "Date": "2017-09-12",
    "Price": 0.002212489
  },
  {
    "Date": "2017-09-13",
    "Price": 0.002212489
  },
  {
    "Date": "2017-09-14",
    "Price": 0.002653354
  },
  {
    "Date": "2017-09-15",
    "Price": 0.002690333
  },
  {
    "Date": "2017-09-18",
    "Price": 0.002721389
  },
  {
    "Date": "2017-09-19",
    "Price": 0.00291949
  },
  {
    "Date": "2017-09-20",
    "Price": 0.003086135
  },
  {
    "Date": "2017-09-21",
    "Price": 0.003125355
  },
  {
    "Date": "2017-09-22",
    "Price": 0.003133599
  },
  {
    "Date": "2017-09-25",
    "Price": 0.003321695
  },
  {
    "Date": "2017-09-26",
    "Price": 0.003321695
  },
  {
    "Date": "2017-09-27",
    "Price": 0.003327418
  },
  {
    "Date": "2017-09-28",
    "Price": 0.003327418
  },
  {
    "Date": "2017-09-29",
    "Price": 0.003679037
  },
  {
    "Date": "2017-10-02",
    "Price": 0.00386033
  },
  {
    "Date": "2017-10-03",
    "Price": 0.003869975
  },
  {
    "Date": "2017-10-04",
    "Price": 0.00387978
  },
  {
    "Date": "2017-10-05",
    "Price": 0.004008606
  },
  {
    "Date": "2017-10-06",
    "Price": 0.004064914
  },
  {
    "Date": "2017-10-09",
    "Price": 0.004691634
  },
  {
    "Date": "2017-10-10",
    "Price": 0.005005074
  },
  {
    "Date": "2017-10-11",
    "Price": 0.005595576
  },
  {
    "Date": "2017-10-12",
    "Price": 0.005631034
  },
  {
    "Date": "2017-10-13",
    "Price": 0.00568282
  },
  {
    "Date": "2017-10-16",
    "Price": 0.005694986
  },
  {
    "Date": "2017-10-17",
    "Price": 0.00568334
  },
  {
    "Date": "2017-10-18",
    "Price": 0.005693025
  },
  {
    "Date": "2017-10-19",
    "Price": 0.0056829
  },
  {
    "Date": "2017-10-20",
    "Price": 0.0056829
  },
  {
    "Date": "2017-10-23",
    "Price": 0.0056829
  },
  {
    "Date": "2017-10-24",
    "Price": 0.005693746
  },
  {
    "Date": "2017-10-25",
    "Price": 0.005703951
  },
  {
    "Date": "2017-10-26",
    "Price": 0.00572272
  },
  {
    "Date": "2017-10-27",
    "Price": 0.005718358
  },
  {
    "Date": "2017-10-30",
    "Price": 0.005722921
  },
  {
    "Date": "2017-10-31",
    "Price": 0.005717878
  },
  {
    "Date": "2017-11-01",
    "Price": 0.005722921
  },
  {
    "Date": "2017-11-02",
    "Price": 0.005727723
  },
  {
    "Date": "2017-11-03",
    "Price": 0.005722921
  },
  {
    "Date": "2017-11-06",
    "Price": 0.005722921
  },
  {
    "Date": "2017-11-07",
    "Price": 0.005722921
  },
  {
    "Date": "2017-11-08",
    "Price": 0.005722921
  },
  {
    "Date": "2017-11-09",
    "Price": 0.005722921
  },
  {
    "Date": "2017-11-10",
    "Price": 0.005725722
  },
  {
    "Date": "2017-11-13",
    "Price": 0.005722921
  },
  {
    "Date": "2017-11-14",
    "Price": 0.005722921
  },
  {
    "Date": "2017-11-15",
    "Price": 0.005722921
  },
  {
    "Date": "2017-11-16",
    "Price": 0.005722921
  },
  {
    "Date": "2017-11-17",
    "Price": 0.004602349
  },
  {
    "Date": "2017-11-20",
    "Price": 0.003701889
  },
  {
    "Date": "2017-11-21",
    "Price": 0.002965513
  },
  {
    "Date": "2017-11-22",
    "Price": 0.002373211
  },
  {
    "Date": "2017-11-23",
    "Price": 0.00190097
  },
  {
    "Date": "2017-11-24",
    "Price": 0.001831134
  },
  {
    "Date": "2017-11-27",
    "Price": 0.001987975
  },
  {
    "Date": "2017-11-28",
    "Price": 0.002153019
  },
  {
    "Date": "2017-11-29",
    "Price": 0.002392661
  },
  {
    "Date": "2017-11-30",
    "Price": 0.002402426
  },
  {
    "Date": "2017-12-01",
    "Price": 0.002397824
  },
  {
    "Date": "2017-12-04",
    "Price": 0.002361205
  },
  {
    "Date": "2017-12-05",
    "Price": 0.00192098
  },
  {
    "Date": "2017-12-06",
    "Price": 0.00191994
  },
  {
    "Date": "2017-12-07",
    "Price": 0.00192098
  },
  {
    "Date": "2017-12-08",
    "Price": 0.00192098
  },
  {
    "Date": "2017-12-11",
    "Price": 0.001758457
  },
  {
    "Date": "2017-12-12",
    "Price": 0.001800919
  },
  {
    "Date": "2017-12-13",
    "Price": 0.001800919
  },
  {
    "Date": "2017-12-14",
    "Price": 0.001800919
  },
  {
    "Date": "2017-12-15",
    "Price": 0.001800919
  },
  {
    "Date": "2017-12-18",
    "Price": 0.001800999
  },
  {
    "Date": "2017-12-19",
    "Price": 0.002045404
  },
  {
    "Date": "2017-12-20",
    "Price": 0.001819368
  },
  {
    "Date": "2017-12-21",
    "Price": 0.001820089
  },
  {
    "Date": "2017-12-27",
    "Price": 0.001816247
  },
  {
    "Date": "2017-12-28",
    "Price": 0.001872436
  },
  {
    "Date": "2017-12-29",
    "Price": 0.002209367
  },
  {
    "Date": "2018-01-02",
    "Price": 0.00188096
  },
  {
    "Date": "2018-01-03",
    "Price": 0.00184246
  },
  {
    "Date": "2018-01-04",
    "Price": 0.001845342
  },
  {
    "Date": "2018-01-05",
    "Price": 0.001892326
  },
  {
    "Date": "2018-01-08",
    "Price": 0.00192098
  },
  {
    "Date": "2018-01-09",
    "Price": 0.00192098
  },
  {
    "Date": "2018-01-10",
    "Price": 0.001924222
  },
  {
    "Date": "2018-01-11",
    "Price": 0.001928024
  },
  {
    "Date": "2018-01-12",
    "Price": 0.001938629
  },
  {
    "Date": "2018-01-15",
    "Price": 0.001942591
  },
  {
    "Date": "2018-01-16",
    "Price": 0.001971486
  },
  {
    "Date": "2018-01-17",
    "Price": 0.00198001
  },
  {
    "Date": "2018-01-18",
    "Price": 0.0020386
  },
  {
    "Date": "2018-01-19",
    "Price": 0.002183754
  },
  {
    "Date": "2018-01-22",
    "Price": 0.002201123
  },
  {
    "Date": "2018-01-23",
    "Price": 0.002201123
  },
  {
    "Date": "2018-01-24",
    "Price": 0.002001021
  },
  {
    "Date": "2018-01-25",
    "Price": 0.002001021
  },
  {
    "Date": "2018-01-26",
    "Price": 0.002001021
  },
  {
    "Date": "2018-01-29",
    "Price": 0.002044723
  },
  {
    "Date": "2018-01-30",
    "Price": 0.002081062
  },
  {
    "Date": "2018-01-31",
    "Price": 0.002081742
  },
  {
    "Date": "2018-02-01",
    "Price": 0.002102553
  },
  {
    "Date": "2018-02-02",
    "Price": 0.002120962
  },
  {
    "Date": "2018-02-05",
    "Price": 0.002122043
  },
  {
    "Date": "2018-02-06",
    "Price": 0.002121082
  },
  {
    "Date": "2018-02-07",
    "Price": 0.002121082
  },
  {
    "Date": "2018-02-08",
    "Price": 0.002121082
  },
  {
    "Date": "2018-02-09",
    "Price": 0.002143654
  },
  {
    "Date": "2018-02-12",
    "Price": 0.002121082
  },
  {
    "Date": "2018-02-13",
    "Price": 0.002121082
  },
  {
    "Date": "2018-02-14",
    "Price": 0.002121082
  },
  {
    "Date": "2018-02-15",
    "Price": 0.002121082
  },
  {
    "Date": "2018-02-16",
    "Price": 0.002121082
  },
  {
    "Date": "2018-02-19",
    "Price": 0.002121082
  },
  {
    "Date": "2018-02-20",
    "Price": 0.002121082
  },
  {
    "Date": "2018-02-22",
    "Price": 0.002121082
  },
  {
    "Date": "2018-02-23",
    "Price": 0.002081062
  },
  {
    "Date": "2018-02-26",
    "Price": 0.002081062
  },
  {
    "Date": "2018-02-27",
    "Price": 0.002102673
  },
  {
    "Date": "2018-02-28",
    "Price": 0.002125084
  },
  {
    "Date": "2018-03-01",
    "Price": 0.002131048
  },
  {
    "Date": "2018-03-02",
    "Price": 0.002161143
  },
  {
    "Date": "2018-03-05",
    "Price": 0.002161103
  },
  {
    "Date": "2018-03-06",
    "Price": 0.002163224
  },
  {
    "Date": "2018-03-07",
    "Price": 0.002168947
  },
  {
    "Date": "2018-03-08",
    "Price": 0.002165105
  },
  {
    "Date": "2018-03-09",
    "Price": 0.002169107
  },
  {
    "Date": "2018-03-12",
    "Price": 0.002169107
  },
  {
    "Date": "2018-03-13",
    "Price": 0.002169107
  },
  {
    "Date": "2018-03-14",
    "Price": 0.002171548
  },
  {
    "Date": "2018-03-15",
    "Price": 0.002181113
  },
  {
    "Date": "2018-03-16",
    "Price": 0.002181113
  },
  {
    "Date": "2018-03-19",
    "Price": 0.002181113
  },
  {
    "Date": "2018-03-20",
    "Price": 0.002187436
  },
  {
    "Date": "2018-03-21",
    "Price": 0.002190878
  },
  {
    "Date": "2018-03-22",
    "Price": 0.002205125
  },
  {
    "Date": "2018-03-23",
    "Price": 0.002225336
  },
  {
    "Date": "2018-03-26",
    "Price": 0.002221133
  },
  {
    "Date": "2018-03-27",
    "Price": 0.002241144
  },
  {
    "Date": "2018-03-28",
    "Price": 0.002241144
  },
  {
    "Date": "2018-03-29",
    "Price": 0.002248948
  },
  {
    "Date": "2018-04-03",
    "Price": 0.002249148
  },
  {
    "Date": "2018-04-04",
    "Price": 0.00225299
  },
  {
    "Date": "2018-04-05",
    "Price": 0.002249468
  },
  {
    "Date": "2018-04-06",
    "Price": 0.002250188
  },
  {
    "Date": "2018-04-09",
    "Price": 0.002249148
  },
  {
    "Date": "2018-04-10",
    "Price": 0.002261154
  },
  {
    "Date": "2018-04-11",
    "Price": 0.002261154
  },
  {
    "Date": "2018-04-12",
    "Price": 0.002264476
  },
  {
    "Date": "2018-04-13",
    "Price": 0.002264596
  },
  {
    "Date": "2018-04-16",
    "Price": 0.002261914
  },
  {
    "Date": "2018-04-17",
    "Price": 0.00227316
  },
  {
    "Date": "2018-04-19",
    "Price": 0.002281164
  },
  {
    "Date": "2018-04-20",
    "Price": 0.002281164
  },
  {
    "Date": "2018-04-23",
    "Price": 0.002281164
  },
  {
    "Date": "2018-04-24",
    "Price": 0.002281164
  },
  {
    "Date": "2018-04-25",
    "Price": 0.002285166
  },
  {
    "Date": "2018-04-26",
    "Price": 0.002285166
  },
  {
    "Date": "2018-04-27",
    "Price": 0.002288928
  },
  {
    "Date": "2018-04-30",
    "Price": 0.002294811
  },
  {
    "Date": "2018-05-02",
    "Price": 0.002306617
  },
  {
    "Date": "2018-05-03",
    "Price": 0.002361965
  },
  {
    "Date": "2018-05-04",
    "Price": 0.002471101
  },
  {
    "Date": "2018-05-07",
    "Price": 0.002546379
  },
  {
    "Date": "2018-05-08",
    "Price": 0.002638226
  },
  {
    "Date": "2018-05-09",
    "Price": 0.002654275
  },
  {
    "Date": "2018-05-10",
    "Price": 0.002682209
  },
  {
    "Date": "2018-05-11",
    "Price": 0.002729073
  },
  {
    "Date": "2018-05-14",
    "Price": 0.002804831
  },
  {
    "Date": "2018-05-15",
    "Price": 0.00282168
  },
  {
    "Date": "2018-05-16",
    "Price": 0.00299817
  },
  {
    "Date": "2018-05-17",
    "Price": 0.003082173
  },
  {
    "Date": "2018-05-18",
    "Price": 0.003123994
  },
  {
    "Date": "2018-05-21",
    "Price": 0.003121993
  },
  {
    "Date": "2018-05-22",
    "Price": 0.003126235
  },
  {
    "Date": "2018-05-23",
    "Price": 0.003156851
  },
  {
    "Date": "2018-05-24",
    "Price": 0.003144885
  },
  {
    "Date": "2018-05-28",
    "Price": 0.003140203
  },
  {
    "Date": "2018-05-29",
    "Price": 0.003142164
  },
  {
    "Date": "2018-05-30",
    "Price": 0.003144205
  },
  {
    "Date": "2018-05-31",
    "Price": 0.003001532
  },
  {
    "Date": "2018-06-01",
    "Price": 0.003001532
  },
  {
    "Date": "2018-06-04",
    "Price": 0.003001532
  },
  {
    "Date": "2018-06-05",
    "Price": 0.002786542
  },
  {
    "Date": "2018-06-06",
    "Price": 0.00242924
  },
  {
    "Date": "2018-06-07",
    "Price": 0.002337753
  },
  {
    "Date": "2018-06-08",
    "Price": 0.002382776
  },
  {
    "Date": "2018-06-11",
    "Price": 0.002401225
  },
  {
    "Date": "2018-06-12",
    "Price": 0.002438044
  },
  {
    "Date": "2018-06-13",
    "Price": 0.002592763
  },
  {
    "Date": "2018-06-14",
    "Price": 0.002601328
  },
  {
    "Date": "2018-06-15",
    "Price": 0.002583799
  },
  {
    "Date": "2018-06-18",
    "Price": 0.002480906
  },
  {
    "Date": "2018-06-19",
    "Price": 0.002403026
  },
  {
    "Date": "2018-06-20",
    "Price": 0.002403787
  },
  {
    "Date": "2018-06-21",
    "Price": 0.002435483
  },
  {
    "Date": "2018-06-22",
    "Price": 0.002402066
  },
  {
    "Date": "2018-06-25",
    "Price": 0.002402066
  },
  {
    "Date": "2018-06-26",
    "Price": 0.001800919
  },
  {
    "Date": "2018-06-27",
    "Price": 0.001924982
  },
  {
    "Date": "2018-06-28",
    "Price": 0.001924982
  },
  {
    "Date": "2018-06-29",
    "Price": 0.002402066
  },
  {
    "Date": "2018-07-02",
    "Price": 0.001940991
  },
  {
    "Date": "2018-07-03",
    "Price": 0.001823811
  },
  {
    "Date": "2018-07-04",
    "Price": 0.001936668
  },
  {
    "Date": "2018-07-05",
    "Price": 0.00192074
  },
  {
    "Date": "2018-07-06",
    "Price": 0.001954237
  },
  {
    "Date": "2018-07-09",
    "Price": 0.001961001
  },
  {
    "Date": "2018-07-10",
    "Price": 0.001976168
  },
  {
    "Date": "2018-07-11",
    "Price": 0.001996299
  },
  {
    "Date": "2018-07-12",
    "Price": 0.002000061
  },
  {
    "Date": "2018-07-13",
    "Price": 0.002001021
  },
  {
    "Date": "2018-07-16",
    "Price": 0.002001021
  },
  {
    "Date": "2018-07-17",
    "Price": 0.002001061
  },
  {
    "Date": "2018-07-18",
    "Price": 0.002001021
  },
  {
    "Date": "2018-07-19",
    "Price": 0.002005023
  },
  {
    "Date": "2018-07-20",
    "Price": 0.002002502
  },
  {
    "Date": "2018-07-23",
    "Price": 0.002003102
  },
  {
    "Date": "2018-07-24",
    "Price": 0.002005023
  },
  {
    "Date": "2018-07-25",
    "Price": 0.002001021
  },
  {
    "Date": "2018-07-26",
    "Price": 0.002001021
  },
  {
    "Date": "2018-07-27",
    "Price": 0.002003022
  },
  {
    "Date": "2018-07-31",
    "Price": 0.002005023
  },
  {
    "Date": "2018-08-01",
    "Price": 0.002009025
  },
  {
    "Date": "2018-08-02",
    "Price": 0.002009065
  },
  {
    "Date": "2018-08-03",
    "Price": 0.002009065
  },
  {
    "Date": "2018-08-06",
    "Price": 0.002009025
  },
  {
    "Date": "2018-08-07",
    "Price": 0.002014028
  },
  {
    "Date": "2018-08-08",
    "Price": 0.002020751
  },
  {
    "Date": "2018-08-09",
    "Price": 0.002036679
  },
  {
    "Date": "2018-08-10",
    "Price": 0.002042122
  },
  {
    "Date": "2018-08-15",
    "Price": 0.002043683
  },
  {
    "Date": "2018-08-16",
    "Price": 0.00205825
  },
  {
    "Date": "2018-08-17",
    "Price": 0.002081062
  },
  {
    "Date": "2018-08-20",
    "Price": 0.002081062
  },
  {
    "Date": "2018-08-21",
    "Price": 0.002085344
  },
  {
    "Date": "2018-08-22",
    "Price": 0.002084744
  },
  {
    "Date": "2018-08-23",
    "Price": 0.002100952
  },
  {
    "Date": "2018-08-24",
    "Price": 0.002103914
  },
  {
    "Date": "2018-08-27",
    "Price": 0.002121082
  },
  {
    "Date": "2018-08-28",
    "Price": 0.002127366
  },
  {
    "Date": "2018-08-29",
    "Price": 0.002137211
  },
  {
    "Date": "2018-08-30",
    "Price": 0.002152498
  },
  {
    "Date": "2018-08-31",
    "Price": 0.002202884
  },
  {
    "Date": "2018-09-03",
    "Price": 0.002242865
  },
  {
    "Date": "2018-09-04",
    "Price": 0.002262034
  },
  {
    "Date": "2018-09-05",
    "Price": 0.002285046
  },
  {
    "Date": "2018-09-06",
    "Price": 0.002337353
  },
  {
    "Date": "2018-09-07",
    "Price": 0.002426999
  },
  {
    "Date": "2018-09-10",
    "Price": 0.002406868
  },
  {
    "Date": "2018-09-11",
    "Price": 0.002405267
  },
  {
    "Date": "2018-09-12",
    "Price": 0.002315262
  },
  {
    "Date": "2018-09-13",
    "Price": 0.002283485
  },
  {
    "Date": "2018-09-14",
    "Price": 0.002001021
  },
  {
    "Date": "2018-09-17",
    "Price": 0.002085544
  },
  {
    "Date": "2018-09-18",
    "Price": 0.002121082
  },
  {
    "Date": "2018-09-19",
    "Price": 0.002121363
  },
  {
    "Date": "2018-09-20",
    "Price": 0.002060492
  },
  {
    "Date": "2018-09-21",
    "Price": 0.002166426
  },
  {
    "Date": "2018-09-24",
    "Price": 0.002166426
  },
  {
    "Date": "2018-09-25",
    "Price": 0.002106115
  },
  {
    "Date": "2018-09-26",
    "Price": 0.002121042
  },
  {
    "Date": "2018-09-27",
    "Price": 0.002121082
  },
  {
    "Date": "2018-09-28",
    "Price": 0.002141093
  },
  {
    "Date": "2018-10-01",
    "Price": 0.002141093
  },
  {
    "Date": "2018-10-02",
    "Price": 0.002187997
  },
  {
    "Date": "2018-10-03",
    "Price": 0.002262395
  },
  {
    "Date": "2018-10-04",
    "Price": 0.002361205
  },
  {
    "Date": "2018-10-05",
    "Price": 0.002470901
  },
  {
    "Date": "2018-10-08",
    "Price": 0.002949865
  },
  {
    "Date": "2018-10-09",
    "Price": 0.003537805
  },
  {
    "Date": "2018-10-10",
    "Price": 0.004242165
  },
  {
    "Date": "2018-10-11",
    "Price": 0.005082594
  },
  {
    "Date": "2018-10-12",
    "Price": 0.004082083
  },
  {
    "Date": "2018-10-15",
    "Price": 0.003281675
  },
  {
    "Date": "2018-10-16",
    "Price": 0.002945223
  },
  {
    "Date": "2018-10-17",
    "Price": 0.003285797
  },
  {
    "Date": "2018-10-18",
    "Price": 0.003286677
  },
  {
    "Date": "2018-10-19",
    "Price": 0.003288798
  },
  {
    "Date": "2018-10-22",
    "Price": 0.003263385
  },
  {
    "Date": "2018-10-23",
    "Price": 0.002863261
  },
  {
    "Date": "2018-10-24",
    "Price": 0.002735356
  },
  {
    "Date": "2018-10-25",
    "Price": 0.002563548
  },
  {
    "Date": "2018-10-26",
    "Price": 0.002404547
  },
  {
    "Date": "2018-10-29",
    "Price": 0.002561507
  },
  {
    "Date": "2018-10-30",
    "Price": 0.002607211
  },
  {
    "Date": "2018-10-31",
    "Price": 0.002682169
  },
  {
    "Date": "2018-11-01",
    "Price": 0.002605129
  },
  {
    "Date": "2018-11-02",
    "Price": 0.002619577
  },
  {
    "Date": "2018-11-05",
    "Price": 0.002597846
  },
  {
    "Date": "2018-11-06",
    "Price": 0.002588081
  },
  {
    "Date": "2018-11-07",
    "Price": 0.002593363
  },
  {
    "Date": "2018-11-08",
    "Price": 0.002593443
  },
  {
    "Date": "2018-11-09",
    "Price": 0.002602848
  },
  {
    "Date": "2018-11-12",
    "Price": 0.002609332
  },
  {
    "Date": "2018-11-13",
    "Price": 0.002714545
  },
  {
    "Date": "2018-11-15",
    "Price": 0.002908884
  },
  {
    "Date": "2018-11-16",
    "Price": 0.003004253
  },
  {
    "Date": "2018-11-19",
    "Price": 0.003090657
  },
  {
    "Date": "2018-11-20",
    "Price": 0.003112268
  },
  {
    "Date": "2018-11-21",
    "Price": 0.003140643
  },
  {
    "Date": "2018-11-22",
    "Price": 0.003141603
  },
  {
    "Date": "2018-11-23",
    "Price": 0.003141603
  },
  {
    "Date": "2018-11-26",
    "Price": 0.003149927
  },
  {
    "Date": "2018-11-27",
    "Price": 0.003183545
  },
  {
    "Date": "2018-11-28",
    "Price": 0.003223005
  },
  {
    "Date": "2018-11-29",
    "Price": 0.003245976
  },
  {
    "Date": "2018-11-30",
    "Price": 0.003271349
  },
  {
    "Date": "2018-12-03",
    "Price": 0.003271349
  },
  {
    "Date": "2018-12-04",
    "Price": 0.003265747
  },
  {
    "Date": "2018-12-05",
    "Price": 0.003268588
  },
  {
    "Date": "2018-12-06",
    "Price": 0.003268388
  },
  {
    "Date": "2018-12-07",
    "Price": 0.003269629
  },
  {
    "Date": "2018-12-10",
    "Price": 0.003276712
  },
  {
    "Date": "2018-12-11",
    "Price": 0.003281595
  },
  {
    "Date": "2018-12-12",
    "Price": 0.003281675
  },
  {
    "Date": "2018-12-13",
    "Price": 0.003287878
  },
  {
    "Date": "2018-12-14",
    "Price": 0.00329208
  },
  {
    "Date": "2018-12-17",
    "Price": 0.003285677
  },
  {
    "Date": "2018-12-18",
    "Price": 0.003286197
  },
  {
    "Date": "2018-12-19",
    "Price": 0.003285677
  },
  {
    "Date": "2018-12-20",
    "Price": 0.003281635
  },
  {
    "Date": "2018-12-21",
    "Price": 0.003261544
  },
  {
    "Date": "2018-12-24",
    "Price": 0.003204075
  },
  {
    "Date": "2018-12-27",
    "Price": 0.003197312
  },
  {
    "Date": "2018-12-28",
    "Price": 0.00319367
  },
  {
    "Date": "2018-12-31",
    "Price": 0.00317402
  },
  {
    "Date": "2019-01-02",
    "Price": 0.003117951
  },
  {
    "Date": "2019-01-03",
    "Price": 0.003117951
  },
  {
    "Date": "2019-01-04",
    "Price": 0.003043153
  },
  {
    "Date": "2019-01-07",
    "Price": 0.002843651
  },
  {
    "Date": "2019-01-08",
    "Price": 0.002805031
  },
  {
    "Date": "2019-01-09",
    "Price": 0.00291889
  },
  {
    "Date": "2019-01-10",
    "Price": 0.003041312
  },
  {
    "Date": "2019-01-11",
    "Price": 0.003270869
  },
  {
    "Date": "2019-01-14",
    "Price": 0.003319334
  },
  {
    "Date": "2019-01-17",
    "Price": 0.003406538
  },
  {
    "Date": "2019-01-21",
    "Price": 0.003458725
  },
  {
    "Date": "2019-01-22",
    "Price": 0.004042183
  },
  {
    "Date": "2019-01-23",
    "Price": 0.003601438
  },
  {
    "Date": "2019-01-24",
    "Price": 0.003608401
  },
  {
    "Date": "2019-01-25",
    "Price": 0.00360464
  },
  {
    "Date": "2019-01-28",
    "Price": 0.003623289
  },
  {
    "Date": "2019-01-29",
    "Price": 0.003621968
  },
  {
    "Date": "2019-01-30",
    "Price": 0.003672994
  },
  {
    "Date": "2019-01-31",
    "Price": 0.003980191
  },
  {
    "Date": "2019-02-01",
    "Price": 0.004002042
  },
  {
    "Date": "2019-02-04",
    "Price": 0.004001882
  },
  {
    "Date": "2019-02-05",
    "Price": 0.00399796
  },
  {
    "Date": "2019-02-06",
    "Price": 0.003796497
  },
  {
    "Date": "2019-02-08",
    "Price": 0.003803581
  },
  {
    "Date": "2019-02-11",
    "Price": 0.00380058
  },
  {
    "Date": "2019-02-12",
    "Price": 0.003681879
  },
  {
    "Date": "2019-02-13",
    "Price": 0.003681599
  },
  {
    "Date": "2019-02-14",
    "Price": 0.003671314
  },
  {
    "Date": "2019-02-15",
    "Price": 0.003681839
  },
  {
    "Date": "2019-02-18",
    "Price": 0.00368436
  },
  {
    "Date": "2019-02-19",
    "Price": 0.003681879
  },
  {
    "Date": "2019-02-20",
    "Price": 0.0036834
  },
  {
    "Date": "2019-02-25",
    "Price": 0.003597836
  },
  {
    "Date": "2019-02-26",
    "Price": 0.003543368
  },
  {
    "Date": "2019-02-27",
    "Price": 0.003002732
  },
  {
    "Date": "2019-02-28",
    "Price": 0.00291981
  },
  {
    "Date": "2019-03-01",
    "Price": 0.002993648
  },
  {
    "Date": "2019-03-04",
    "Price": 0.002790144
  },
  {
    "Date": "2019-03-05",
    "Price": 0.00280143
  },
  {
    "Date": "2019-03-06",
    "Price": 0.003002572
  },
  {
    "Date": "2019-03-07",
    "Price": 0.003001532
  },
  {
    "Date": "2019-03-08",
    "Price": 0.003001452
  },
  {
    "Date": "2019-03-11",
    "Price": 0.002787983
  },
  {
    "Date": "2019-03-12",
    "Price": 0.002844612
  },
  {
    "Date": "2019-03-13",
    "Price": 0.002898599
  },
  {
    "Date": "2019-03-14",
    "Price": 0.002921491
  },
  {
    "Date": "2019-03-15",
    "Price": 0.002921491
  },
  {
    "Date": "2019-03-18",
    "Price": 0.002917329
  },
  {
    "Date": "2019-03-19",
    "Price": 0.002917329
  },
  {
    "Date": "2019-03-20",
    "Price": 0.002811795
  },
  {
    "Date": "2019-03-21",
    "Price": 0.00290044
  },
  {
    "Date": "2019-03-22",
    "Price": 0.002895998
  },
  {
    "Date": "2019-03-25",
    "Price": 0.002845252
  },
  {
    "Date": "2019-03-26",
    "Price": 0.002818919
  },
  {
    "Date": "2019-03-27",
    "Price": 0.002907084
  },
  {
    "Date": "2019-03-28",
    "Price": 0.003160413
  },
  {
    "Date": "2019-03-29",
    "Price": 0.003192829
  },
  {
    "Date": "2019-04-01",
    "Price": 0.003262825
  },
  {
    "Date": "2019-04-02",
    "Price": 0.003260304
  },
  {
    "Date": "2019-04-03",
    "Price": 0.003201474
  },
  {
    "Date": "2019-04-04",
    "Price": 0.003201634
  },
  {
    "Date": "2019-04-05",
    "Price": 0.003201674
  },
  {
    "Date": "2019-04-08",
    "Price": 0.003287638
  },
  {
    "Date": "2019-04-09",
    "Price": 0.003308168
  },
  {
    "Date": "2019-04-10",
    "Price": 0.003309689
  },
  {
    "Date": "2019-04-11",
    "Price": 0.003309689
  },
  {
    "Date": "2019-04-12",
    "Price": 0.0032926
  },
  {
    "Date": "2019-04-15",
    "Price": 0.003313971
  },
  {
    "Date": "2019-04-16",
    "Price": 0.003322496
  },
  {
    "Date": "2019-04-17",
    "Price": 0.003342186
  },
  {
    "Date": "2019-04-23",
    "Price": 0.00341014
  },
  {
    "Date": "2019-04-24",
    "Price": 0.003551212
  },
  {
    "Date": "2019-04-25",
    "Price": 0.00362601
  },
  {
    "Date": "2019-04-26",
    "Price": 0.00364518
  },
  {
    "Date": "2019-04-29",
    "Price": 0.003807743
  },
  {
    "Date": "2019-04-30",
    "Price": 0.003965984
  },
  {
    "Date": "2019-05-02",
    "Price": 0.004031898
  },
  {
    "Date": "2019-05-03",
    "Price": 0.004066755
  },
  {
    "Date": "2019-05-06",
    "Price": 0.004002923
  },
  {
    "Date": "2019-05-07",
    "Price": 0.004010607
  },
  {
    "Date": "2019-05-08",
    "Price": 0.004014769
  },
  {
    "Date": "2019-05-09",
    "Price": 0.004048786
  },
  {
    "Date": "2019-05-10",
    "Price": 0.004162804
  },
  {
    "Date": "2019-05-13",
    "Price": 0.00419362
  },
  {
    "Date": "2019-05-14",
    "Price": 0.004412292
  },
  {
    "Date": "2019-05-15",
    "Price": 0.004521948
  },
  {
    "Date": "2019-05-16",
    "Price": 0.004789124
  },
  {
    "Date": "2019-05-17",
    "Price": 0.004886734
  },
  {
    "Date": "2019-05-20",
    "Price": 0.00487845
  },
  {
    "Date": "2019-05-21",
    "Price": 0.004568852
  },
  {
    "Date": "2019-05-22",
    "Price": 0.004581338
  },
  {
    "Date": "2019-05-23",
    "Price": 0.004716247
  },
  {
    "Date": "2019-05-24",
    "Price": 0.004704161
  },
  {
    "Date": "2019-05-27",
    "Price": 0.004708323
  },
  {
    "Date": "2019-05-28",
    "Price": 0.004763831
  },
  {
    "Date": "2019-05-29",
    "Price": 0.005003553
  },
  {
    "Date": "2019-05-30",
    "Price": 0.005206217
  },
  {
    "Date": "2019-05-31",
    "Price": 0.005599898
  },
  {
    "Date": "2019-06-03",
    "Price": 0.005602859
  },
  {
    "Date": "2019-06-04",
    "Price": 0.005602339
  },
  {
    "Date": "2019-06-05",
    "Price": 0.00560402
  },
  {
    "Date": "2019-06-06",
    "Price": 0.005494364
  },
  {
    "Date": "2019-06-07",
    "Price": 0.005402757
  },
  {
    "Date": "2019-06-10",
    "Price": 0.005362337
  },
  {
    "Date": "2019-06-11",
    "Price": 0.005597416
  },
  {
    "Date": "2019-06-12",
    "Price": 0.005602859
  },
  {
    "Date": "2019-06-13",
    "Price": 0.00560414
  },
  {
    "Date": "2019-06-14",
    "Price": 0.005769704
  },
  {
    "Date": "2019-06-17",
    "Price": 0.006199003
  },
  {
    "Date": "2019-06-18",
    "Price": 0.006203166
  },
  {
    "Date": "2019-06-19",
    "Price": 0.006203166
  },
  {
    "Date": "2019-06-20",
    "Price": 0.006577757
  },
  {
    "Date": "2019-06-21",
    "Price": 0.006862502
  },
  {
    "Date": "2019-06-24",
    "Price": 0.006845533
  },
  {
    "Date": "2019-06-25",
    "Price": 0.006869266
  },
  {
    "Date": "2019-06-26",
    "Price": 0.005502808
  },
  {
    "Date": "2019-06-27",
    "Price": 0.005220784
  },
  {
    "Date": "2019-06-28",
    "Price": 0.005502808
  },
  {
    "Date": "2019-07-01",
    "Price": 0.005223226
  },
  {
    "Date": "2019-07-02",
    "Price": 0.005206937
  },
  {
    "Date": "2019-07-03",
    "Price": 0.005287258
  },
  {
    "Date": "2019-07-04",
    "Price": 0.005601539
  },
  {
    "Date": "2019-07-05",
    "Price": 0.005602859
  },
  {
    "Date": "2019-07-08",
    "Price": 0.005602859
  },
  {
    "Date": "2019-07-09",
    "Price": 0.005609543
  },
  {
    "Date": "2019-07-10",
    "Price": 0.005842982
  },
  {
    "Date": "2019-07-11",
    "Price": 0.005963043
  },
  {
    "Date": "2019-07-15",
    "Price": 0.006293572
  },
  {
    "Date": "2019-07-16",
    "Price": 0.006303217
  },
  {
    "Date": "2019-07-17",
    "Price": 0.00631074
  },
  {
    "Date": "2019-07-18",
    "Price": 0.006303217
  },
  {
    "Date": "2019-07-19",
    "Price": 0.006303217
  },
  {
    "Date": "2019-07-22",
    "Price": 0.006415634
  },
  {
    "Date": "2019-07-23",
    "Price": 0.006420356
  },
  {
    "Date": "2019-07-24",
    "Price": 0.006404028
  },
  {
    "Date": "2019-07-25",
    "Price": 0.006423278
  },
  {
    "Date": "2019-07-26",
    "Price": 0.006429601
  },
  {
    "Date": "2019-07-29",
    "Price": 0.006444049
  },
  {
    "Date": "2019-07-30",
    "Price": 0.006483309
  },
  {
    "Date": "2019-07-31",
    "Price": 0.006512563
  },
  {
    "Date": "2019-08-01",
    "Price": 0.006522168
  },
  {
    "Date": "2019-08-02",
    "Price": 0.006944704
  },
  {
    "Date": "2019-08-05",
    "Price": 0.007042954
  },
  {
    "Date": "2019-08-06",
    "Price": 0.007125156
  },
  {
    "Date": "2019-08-07",
    "Price": 0.007982073
  },
  {
    "Date": "2019-08-08",
    "Price": 0.008297154
  },
  {
    "Date": "2019-08-09",
    "Price": 0.008547922
  },
  {
    "Date": "2019-08-14",
    "Price": 0.008604391
  },
  {
    "Date": "2019-08-15",
    "Price": 0.008693316
  },
  {
    "Date": "2019-08-16",
    "Price": 0.008693316
  },
  {
    "Date": "2019-08-19",
    "Price": 0.008023174
  },
  {
    "Date": "2019-08-20",
    "Price": 0.00760388
  },
  {
    "Date": "2019-08-21",
    "Price": 0.00758431
  },
  {
    "Date": "2019-08-22",
    "Price": 0.007483819
  },
  {
    "Date": "2019-08-23",
    "Price": 0.007403778
  },
  {
    "Date": "2019-08-26",
    "Price": 0.007403778
  },
  {
    "Date": "2019-08-27",
    "Price": 0.007403778
  },
  {
    "Date": "2019-08-28",
    "Price": 0.007161735
  },
  {
    "Date": "2019-08-29",
    "Price": 0.007003574
  },
  {
    "Date": "2019-08-30",
    "Price": 0.007003574
  },
  {
    "Date": "2019-09-02",
    "Price": 0.007003574
  },
  {
    "Date": "2019-09-03",
    "Price": 0.006993169
  },
  {
    "Date": "2019-09-04",
    "Price": 0.007019942
  },
  {
    "Date": "2019-09-05",
    "Price": 0.007128238
  },
  {
    "Date": "2019-09-06",
    "Price": 0.007168778
  },
  {
    "Date": "2019-09-09",
    "Price": 0.007339505
  },
  {
    "Date": "2019-09-10",
    "Price": 0.00760328
  },
  {
    "Date": "2019-09-11",
    "Price": 0.007829716
  },
  {
    "Date": "2019-09-12",
    "Price": 0.009384789
  },
  {
    "Date": "2019-09-13",
    "Price": 0.010021834
  },
  {
    "Date": "2019-09-16",
    "Price": 0.009722041
  },
  {
    "Date": "2019-09-17",
    "Price": 0.011047798
  },
  {
    "Date": "2019-09-18",
    "Price": 0.011245739
  },
  {
    "Date": "2019-09-19",
    "Price": 0.011245739
  },
  {
    "Date": "2019-09-20",
    "Price": 0.013486883
  },
  {
    "Date": "2019-09-23",
    "Price": 0.013907657
  },
  {
    "Date": "2019-09-24",
    "Price": 0.014021195
  },
  {
    "Date": "2019-09-25",
    "Price": 0.014021195
  },
  {
    "Date": "2019-09-26",
    "Price": 0.011988398
  },
  {
    "Date": "2019-09-27",
    "Price": 0.010025116
  },
  {
    "Date": "2019-09-30",
    "Price": 0.010010829
  },
  {
    "Date": "2019-10-01",
    "Price": 0.010216734
  },
  {
    "Date": "2019-10-02",
    "Price": 0.011995081
  },
  {
    "Date": "2019-10-03",
    "Price": 0.012006127
  },
  {
    "Date": "2019-10-04",
    "Price": 0.014011991
  },
  {
    "Date": "2019-10-07",
    "Price": 0.013816291
  },
  {
    "Date": "2019-10-08",
    "Price": 0.013829618
  },
  {
    "Date": "2019-10-09",
    "Price": 0.013614268
  },
  {
    "Date": "2019-10-10",
    "Price": 0.013606944
  },
  {
    "Date": "2019-10-11",
    "Price": 0.013569885
  },
  {
    "Date": "2019-10-14",
    "Price": 0.013385551
  },
  {
    "Date": "2019-10-15",
    "Price": 0.013219746
  },
  {
    "Date": "2019-10-16",
    "Price": 0.01320674
  },
  {
    "Date": "2019-10-17",
    "Price": 0.013217705
  },
  {
    "Date": "2019-10-18",
    "Price": 0.01320678
  },
  {
    "Date": "2019-10-21",
    "Price": 0.013237555
  },
  {
    "Date": "2019-10-22",
    "Price": 0.013329442
  },
  {
    "Date": "2019-10-23",
    "Price": 0.013432415
  },
  {
    "Date": "2019-10-24",
    "Price": 0.01320806
  },
  {
    "Date": "2019-10-28",
    "Price": 0.013880403
  },
  {
    "Date": "2019-10-29",
    "Price": 0.0143432
  },
  {
    "Date": "2019-10-30",
    "Price": 0.014351644
  },
  {
    "Date": "2019-10-31",
    "Price": 0.014495557
  },
  {
    "Date": "2019-11-01",
    "Price": 0.014799793
  },
  {
    "Date": "2019-11-04",
    "Price": 0.014779422
  },
  {
    "Date": "2019-11-05",
    "Price": 0.014759212
  },
  {
    "Date": "2019-11-06",
    "Price": 0.014795711
  },
  {
    "Date": "2019-11-07",
    "Price": 0.014769017
  },
  {
    "Date": "2019-11-08",
    "Price": 0.014767536
  },
  {
    "Date": "2019-11-11",
    "Price": 0.014727276
  },
  {
    "Date": "2019-11-12",
    "Price": 0.014502121
  },
  {
    "Date": "2019-11-13",
    "Price": 0.014605333
  },
  {
    "Date": "2019-11-14",
    "Price": 0.014656119
  },
  {
    "Date": "2019-11-15",
    "Price": 0.014572637
  },
  {
    "Date": "2019-11-18",
    "Price": 0.013606944
  },
  {
    "Date": "2019-11-19",
    "Price": 0.013601301
  },
  {
    "Date": "2019-11-20",
    "Price": 0.013588494
  },
  {
    "Date": "2019-11-21",
    "Price": 0.012468523
  },
  {
    "Date": "2019-11-22",
    "Price": 0.013406842
  },
  {
    "Date": "2019-11-25",
    "Price": 0.013448863
  },
  {
    "Date": "2019-11-26",
    "Price": 0.013563522
  },
  {
    "Date": "2019-11-27",
    "Price": 0.013793759
  },
  {
    "Date": "2019-11-28",
    "Price": 0.013812729
  },
  {
    "Date": "2019-11-29",
    "Price": 0.014028079
  },
  {
    "Date": "2019-12-02",
    "Price": 0.014387902
  },
  {
    "Date": "2019-12-03",
    "Price": 0.014407753
  },
  {
    "Date": "2019-12-04",
    "Price": 0.014297696
  },
  {
    "Date": "2019-12-05",
    "Price": 0.014265
  },
  {
    "Date": "2019-12-06",
    "Price": 0.014381739
  },
  {
    "Date": "2019-12-09",
    "Price": 0.013636279
  },
  {
    "Date": "2019-12-10",
    "Price": 0.014159506
  },
  {
    "Date": "2019-12-11",
    "Price": 0.01420701
  },
  {
    "Date": "2019-12-12",
    "Price": 0.014233023
  },
  {
    "Date": "2019-12-13",
    "Price": 0.014280488
  },
  {
    "Date": "2019-12-16",
    "Price": 0.014407352
  },
  {
    "Date": "2019-12-17",
    "Price": 0.014557229
  },
  {
    "Date": "2019-12-18",
    "Price": 0.014505282
  },
  {
    "Date": "2019-12-19",
    "Price": 0.014920494
  },
  {
    "Date": "2019-12-20",
    "Price": 0.014007148
  },
  {
    "Date": "2019-12-24",
    "Price": 0.014229822
  },
  {
    "Date": "2019-12-27",
    "Price": 0.014229822
  },
  {
    "Date": "2019-12-30",
    "Price": 0.014276766
  },
  {
    "Date": "2019-12-31",
    "Price": 0.014607575
  },
  {
    "Date": "2020-01-02",
    "Price": 0.014436447
  },
  {
    "Date": "2020-01-03",
    "Price": 0.014426042
  },
  {
    "Date": "2020-01-06",
    "Price": 0.014721673
  },
  {
    "Date": "2020-01-07",
    "Price": 0.014827567
  },
  {
    "Date": "2020-01-08",
    "Price": 0.014602852
  },
  {
    "Date": "2020-01-09",
    "Price": 0.014407352
  },
  {
    "Date": "2020-01-10",
    "Price": 0.014407072
  },
  {
    "Date": "2020-01-13",
    "Price": 0.014407552
  },
  {
    "Date": "2020-01-14",
    "Price": 0.014721673
  },
  {
    "Date": "2020-01-15",
    "Price": 0.014601692
  },
  {
    "Date": "2020-01-16",
    "Price": 0.014061616
  },
  {
    "Date": "2020-01-17",
    "Price": 0.013612787
  },
  {
    "Date": "2020-01-20",
    "Price": 0.013606944
  },
  {
    "Date": "2020-01-21",
    "Price": 0.014774019
  },
  {
    "Date": "2020-01-22",
    "Price": 0.015585674
  },
  {
    "Date": "2020-01-23",
    "Price": 0.015585674
  },
  {
    "Date": "2020-01-24",
    "Price": 0.015607965
  },
  {
    "Date": "2020-01-27",
    "Price": 0.015807387
  },
  {
    "Date": "2020-01-28",
    "Price": 0.01622416
  },
  {
    "Date": "2020-01-29",
    "Price": 0.017489205
  },
  {
    "Date": "2020-01-30",
    "Price": 0.018896483
  },
  {
    "Date": "2020-01-31",
    "Price": 0.019205041
  },
  {
    "Date": "2020-02-03",
    "Price": 0.019130122
  },
  {
    "Date": "2020-02-04",
    "Price": 0.016252494
  },
  {
    "Date": "2020-02-05",
    "Price": 0.016008169
  },
  {
    "Date": "2020-02-06",
    "Price": 0.016722814
  },
  {
    "Date": "2020-02-07",
    "Price": 0.017199977
  },
  {
    "Date": "2020-02-10",
    "Price": 0.017319959
  },
  {
    "Date": "2020-02-11",
    "Price": 0.018201369
  },
  {
    "Date": "2020-02-12",
    "Price": 0.020270344
  },
  {
    "Date": "2020-02-13",
    "Price": 0.02081106
  },
  {
    "Date": "2020-02-14",
    "Price": 0.02320112
  },
  {
    "Date": "2020-02-17",
    "Price": 0.022012033
  },
  {
    "Date": "2020-02-18",
    "Price": 0.020155326
  },
  {
    "Date": "2020-02-19",
    "Price": 0.019055524
  },
  {
    "Date": "2020-02-20",
    "Price": 0.017609146
  },
  {
    "Date": "2020-02-24",
    "Price": 0.017251044
  },
  {
    "Date": "2020-02-25",
    "Price": 0.017457589
  },
  {
    "Date": "2020-02-26",
    "Price": 0.018989851
  },
  {
    "Date": "2020-02-27",
    "Price": 0.019214766
  },
  {
    "Date": "2020-02-28",
    "Price": 0.019285842
  },
  {
    "Date": "2020-03-02",
    "Price": 0.019309454
  },
  {
    "Date": "2020-03-03",
    "Price": 0.020122989
  },
  {
    "Date": "2020-03-04",
    "Price": 0.020013974
  },
  {
    "Date": "2020-03-05",
    "Price": 0.020010212
  },
  {
    "Date": "2020-03-06",
    "Price": 0.019944338
  },
  {
    "Date": "2020-03-09",
    "Price": 0.020213836
  },
  {
    "Date": "2020-03-10",
    "Price": 0.020020377
  },
  {
    "Date": "2020-03-11",
    "Price": 0.021200299
  },
  {
    "Date": "2020-03-12",
    "Price": 0.021210824
  },
  {
    "Date": "2020-03-13",
    "Price": 0.021298629
  },
  {
    "Date": "2020-03-16",
    "Price": 0.017057225
  },
  {
    "Date": "2020-03-17",
    "Price": 0.015207961
  },
  {
    "Date": "2020-03-18",
    "Price": 0.015170902
  },
  {
    "Date": "2020-03-19",
    "Price": 0.015211643
  },
  {
    "Date": "2020-03-20",
    "Price": 0.018209293
  },
  {
    "Date": "2020-03-23",
    "Price": 0.017455868
  },
  {
    "Date": "2020-03-24",
    "Price": 0.017531867
  },
  {
    "Date": "2020-03-25",
    "Price": 0.015552537
  },
  {
    "Date": "2020-03-26",
    "Price": 0.015101827
  },
  {
    "Date": "2020-03-27",
    "Price": 0.014611977
  },
  {
    "Date": "2020-03-30",
    "Price": 0.015204399
  },
  {
    "Date": "2020-03-31",
    "Price": 0.015204399
  },
  {
    "Date": "2020-04-01",
    "Price": 0.015038835
  },
  {
    "Date": "2020-04-02",
    "Price": 0.015207761
  },
  {
    "Date": "2020-04-03",
    "Price": 0.014807557
  },
  {
    "Date": "2020-04-06",
    "Price": 0.014807557
  },
  {
    "Date": "2020-04-07",
    "Price": 0.014705224
  },
  {
    "Date": "2020-04-08",
    "Price": 0.014591446
  },
  {
    "Date": "2020-04-09",
    "Price": 0.014683133
  },
  {
    "Date": "2020-04-14",
    "Price": 0.014683133
  },
  {
    "Date": "2020-04-15",
    "Price": 0.015464812
  },
  {
    "Date": "2020-04-16",
    "Price": 0.015491906
  },
  {
    "Date": "2020-04-17",
    "Price": 0.015611127
  },
  {
    "Date": "2020-04-20",
    "Price": 0.016008169
  },
  {
    "Date": "2020-04-21",
    "Price": 0.016808578
  },
  {
    "Date": "2020-04-22",
    "Price": 0.017208822
  },
  {
    "Date": "2020-04-23",
    "Price": 0.017228792
  },
  {
    "Date": "2020-04-24",
    "Price": 0.017208782
  },
  {
    "Date": "2020-04-27",
    "Price": 0.016808578
  },
  {
    "Date": "2020-04-28",
    "Price": 0.017102248
  },
  {
    "Date": "2020-04-29",
    "Price": 0.017227912
  },
  {
    "Date": "2020-04-30",
    "Price": 0.016808578
  },
  {
    "Date": "2020-05-04",
    "Price": 0.01720546
  },
  {
    "Date": "2020-05-05",
    "Price": 0.016745345
  },
  {
    "Date": "2020-05-06",
    "Price": 0.016579141
  },
  {
    "Date": "2020-05-07",
    "Price": 0.016408374
  },
  {
    "Date": "2020-05-08",
    "Price": 0.01651955
  },
  {
    "Date": "2020-05-11",
    "Price": 0.01720478
  },
  {
    "Date": "2020-05-12",
    "Price": 0.018414437
  },
  {
    "Date": "2020-05-13",
    "Price": 0.018809439
  },
  {
    "Date": "2020-05-14",
    "Price": 0.021293987
  },
  {
    "Date": "2020-05-15",
    "Price": 0.022434449
  },
  {
    "Date": "2020-05-18",
    "Price": 0.02682565
  },
  {
    "Date": "2020-05-19",
    "Price": 0.026895685
  },
  {
    "Date": "2020-05-20",
    "Price": 0.027229456
  },
  {
    "Date": "2020-05-21",
    "Price": 0.027233898
  },
  {
    "Date": "2020-05-22",
    "Price": 0.029331929
  },
  {
    "Date": "2020-05-26",
    "Price": 0.030506968
  },
  {
    "Date": "2020-05-27",
    "Price": 0.033803571
  },
  {
    "Date": "2020-05-28",
    "Price": 0.03401736
  },
  {
    "Date": "2020-05-29",
    "Price": 0.033984023
  },
  {
    "Date": "2020-06-01",
    "Price": 0.036018381
  },
  {
    "Date": "2020-06-02",
    "Price": 0.036887665
  },
  {
    "Date": "2020-06-03",
    "Price": 0.037644651
  },
  {
    "Date": "2020-06-04",
    "Price": 0.037614195
  },
  {
    "Date": "2020-06-05",
    "Price": 0.037177012
  },
  {
    "Date": "2020-06-08",
    "Price": 0.036493583
  },
  {
    "Date": "2020-06-09",
    "Price": 0.034040291
  },
  {
    "Date": "2020-06-10",
    "Price": 0.03401736
  },
  {
    "Date": "2020-06-11",
    "Price": 0.03401736
  },
  {
    "Date": "2020-06-12",
    "Price": 0.03401736
  },
  {
    "Date": "2020-06-15",
    "Price": 0.03401736
  },
  {
    "Date": "2020-06-16",
    "Price": 0.03401736
  },
  {
    "Date": "2020-06-17",
    "Price": 0.033628281
  },
  {
    "Date": "2020-06-18",
    "Price": 0.03401712
  },
  {
    "Date": "2020-06-19",
    "Price": 0.03401736
  },
  {
    "Date": "2020-06-22",
    "Price": 0.034862431
  },
  {
    "Date": "2020-06-23",
    "Price": 0.034015199
  },
  {
    "Date": "2020-06-24",
    "Price": 0.03401736
  },
  {
    "Date": "2020-06-25",
    "Price": 0.032868133
  },
  {
    "Date": "2020-06-26",
    "Price": 0.032812985
  },
  {
    "Date": "2020-08-03",
    "Price": 0.032812985
  },
  {
    "Date": "2020-08-03 00:00:00",
    "Price": 0.032812985
  }
]