[
  {
    "Date": "2025-11-25",
    "Volume": 199217,
    "Close": 17.75,
    "Change": NaN,
    "Change%": NaN
  },
  {
    "Date": "2025-11-19",
    "Volume": 512,
    "Close": 17.75,
    "Change": NaN,
    "Change%": NaN
  },
  {
    "Date": "2025-11-12",
    "Volume": 8125,
    "Close": 17.75,
    "Change": NaN,
    "Change%": NaN
  },
  {
    "Date": "2025-11-06",
    "Volume": 26881,
    "Close": 17.75,
    "Change": NaN,
    "Change%": NaN
  },
  {
    "Date": "2025-10-13",
    "Volume": 1017,
    "Close": 17.75,
    "Change": 0.05,
    "Change%": "+0.28%"
  },
  {
    "Date": "2025-10-10",
    "Volume": 1000,
    "Close": 17.7,
    "Change": NaN,
    "Change%": NaN
  },
  {
    "Date": "2025-10-06",
    "Volume": 1000,
    "Close": 17.7,
    "Change": 0.13,
    "Change%": "+0.74%"
  },
  {
    "Date": "2025-09-25",
    "Volume": 6409,
    "Close": 17.57,
    "Change": 0.01,
    "Change%": "+0.06%"
  },
  {
    "Date": "2025-09-09",
    "Volume": 860,
    "Close": 17.56,
    "Change": NaN,
    "Change%": NaN
  },
  {
    "Date": "2025-09-08",
    "Volume": 3536,
    "Close": 17.56,
    "Change": NaN,
    "Change%": NaN
  }
]