[
  {
    "Date": "2025-07-25",
    "Volume": 1972,
    "Close": 3.5,
    "Change": NaN,
    "Change%": NaN
  },
  {
    "Date": "2025-07-23",
    "Volume": 14787,
    "Close": 3.5,
    "Change": NaN,
    "Change%": NaN
  },
  {
    "Date": "2025-06-09",
    "Volume": 2185509,
    "Close": 3.5,
    "Change": NaN,
    "Change%": NaN
  },
  {
    "Date": "2025-03-31",
    "Volume": 3394,
    "Close": 3.5,
    "Change": NaN,
    "Change%": NaN
  },
  {
    "Date": "2025-02-10",
    "Volume": 454,
    "Close": 3.5,
    "Change": NaN,
    "Change%": NaN
  },
  {
    "Date": "2025-01-27",
    "Volume": 7892,
    "Close": 3.5,
    "Change": NaN,
    "Change%": NaN
  },
  {
    "Date": "2025-01-09",
    "Volume": 454,
    "Close": 3.5,
    "Change": NaN,
    "Change%": NaN
  },
  {
    "Date": "2024-12-06",
    "Volume": 271,
    "Close": 3.5,
    "Change": NaN,
    "Change%": NaN
  },
  {
    "Date": "2024-12-05",
    "Volume": 1063,
    "Close": 3.5,
    "Change": NaN,
    "Change%": NaN
  },
  {
    "Date": "2024-11-07",
    "Volume": 1472,
    "Close": 3.5,
    "Change": NaN,
    "Change%": NaN
  }
]