[
  {
    "Code": "OCH",
    "Name": "Olympia Capital Holdings Limited",
    "M. Cap.": "290M",
    "Close": 7.26,
    "YTD": "+159%"
  },
  {
    "Code": "PORT",
    "Name": "East African Portland Cement Co. Ltd",
    "M. Cap.": "5.83B",
    "Close": 64.75,
    "YTD": "+112%"
  },
  {
    "Code": "TCL",
    "Name": "Trans Century Limited",
    "M. Cap.": "266M",
    "Close": 0.71,
    "YTD": "+82.1%"
  },
  {
    "Code": "SKL",
    "Name": "Shri Krishana Overseas Ltd",
    "M. Cap.": "412M",
    "Close": 8.16,
    "YTD": "+38.3%"
  },
  {
    "Code": "CABL",
    "Name": "East African Cables Limited",
    "M. Cap.": "253M",
    "Close": 1.0,
    "YTD": "-7.41%"
  },
  {
    "Code": "BAMB",
    "Name": "Bamburi Cement Limited",
    "M. Cap.": "17.1B",
    "Close": 47.2,
    "YTD": "-14.2%"
  }
]