[
  {
    "Date": "2025-11-28",
    "Volume": 1596023,
    "Close": 13.2,
    "Change": -0.3,
    "Change%": "-2.22%"
  },
  {
    "Date": "2025-11-27",
    "Volume": 1886640,
    "Close": 13.5,
    "Change": 0.3,
    "Change%": "+2.27%"
  },
  {
    "Date": "2025-11-26",
    "Volume": 1138842,
    "Close": 13.2,
    "Change": 0.2,
    "Change%": "+1.54%"
  },
  {
    "Date": "2025-11-25",
    "Volume": 326352,
    "Close": 13.0,
    "Change": NaN,
    "Change%": NaN
  },
  {
    "Date": "2025-11-24",
    "Volume": 1087180,
    "Close": 13.0,
    "Change": -0.5,
    "Change%": "-3.70%"
  },
  {
    "Date": "2025-11-21",
    "Volume": 1245368,
    "Close": 13.5,
    "Change": NaN,
    "Change%": NaN
  },
  {
    "Date": "2025-11-20",
    "Volume": 797031,
    "Close": 13.5,
    "Change": NaN,
    "Change%": NaN
  },
  {
    "Date": "2025-11-19",
    "Volume": 1786562,
    "Close": 13.5,
    "Change": -0.5,
    "Change%": "-3.57%"
  },
  {
    "Date": "2025-11-18",
    "Volume": 1033314,
    "Close": 14.0,
    "Change": 0.5,
    "Change%": "+3.70%"
  },
  {
    "Date": "2025-11-17",
    "Volume": 280394,
    "Close": 13.5,
    "Change": NaN,
    "Change%": NaN
  }
]