[
  {
    "Growth & Valuation": "Earnings Per Share",
    "Growth & Valuation.1": "525.24"
  },
  {
    "Growth & Valuation": "Price/Earning Ratio",
    "Growth & Valuation.1": "9.51"
  },
  {
    "Growth & Valuation": "Dividend Per Share",
    "Growth & Valuation.1": "254.60"
  },
  {
    "Growth & Valuation": "Dividend Yield",
    "Growth & Valuation.1": "5.1%"
  },
  {
    "Growth & Valuation": "Shares Outstanding",
    "Growth & Valuation.1": "57.8M"
  },
  {
    "Growth & Valuation": "Market Capitalization",
    "Growth & Valuation.1": "289B"
  }
]