[
  {
    "Code": "ECOC",
    "Name": "Ecobank C\\xc3\\xb4te d\\xe2\\x80\\x99Ivoire",
    "M. Cap.": "864B",
    "Close": 15700,
    "YTD": "+78.5%"
  },
  {
    "Code": "NSBC",
    "Name": "Nsia Banque C\\xc3\\xb4te d\\xe2\\x80\\x99Ivoire",
    "M. Cap.": "297B",
    "Close": 11995,
    "YTD": "+69.2%"
  },
  {
    "Code": "BOAS",
    "Name": "Bank of Africa - Senegal",
    "M. Cap.": "189B",
    "Close": 5250,
    "YTD": "+66.7%"
  },
  {
    "Code": "SIBC",
    "Name": "Societe Ivoirienne de Banque",
    "M. Cap.": "560B",
    "Close": 5600,
    "YTD": "+57.5%"
  },
  {
    "Code": "ETIT",
    "Name": "Ecobank Transnational Inc",
    "M. Cap.": "434B",
    "Close": 24,
    "YTD": "+50%"
  },
  {
    "Code": "BOAC",
    "Name": "Bank of Africa - C\\xc3\\xb4te d\\xe2\\x80\\x99Ivoire",
    "M. Cap.": "288B",
    "Close": 7200,
    "YTD": "+44.1%"
  },
  {
    "Code": "BICC",
    "Name": "BICI C\\xc3\\xb4te d\\xe2\\x80\\x99Ivoire",
    "M. Cap.": "325B",
    "Close": 19490,
    "YTD": "+39.2%"
  },
  {
    "Code": "BOAB",
    "Name": "Bank of Africa - Benin",
    "M. Cap.": "201B",
    "Close": 4945,
    "YTD": "+34.2%"
  },
  {
    "Code": "ORGT",
    "Name": "Oragroup Togo",
    "M. Cap.": "173B",
    "Close": 2495,
    "YTD": "+30%"
  },
  {
    "Code": "SGBC",
    "Name": "SGB C\\xc3\\xb4te d\\xe2\\x80\\x99Ivoire",
    "M. Cap.": "839B",
    "Close": 26955,
    "YTD": "+28.4%"
  }
]