[
  {
    "Date": "2025-11-25",
    "Volume": 7559,
    "Close": 1505,
    "Change": 30.0,
    "Change%": "+2.03%"
  },
  {
    "Date": "2025-11-24",
    "Volume": 4317,
    "Close": 1475,
    "Change": -5.0,
    "Change%": "-0.34%"
  },
  {
    "Date": "2025-11-21",
    "Volume": 3416,
    "Close": 1480,
    "Change": -35.0,
    "Change%": "-2.31%"
  },
  {
    "Date": "2025-11-20",
    "Volume": 5822,
    "Close": 1515,
    "Change": NaN,
    "Change%": NaN
  },
  {
    "Date": "2025-11-19",
    "Volume": 1747,
    "Close": 1515,
    "Change": NaN,
    "Change%": NaN
  },
  {
    "Date": "2025-11-18",
    "Volume": 3124,
    "Close": 1515,
    "Change": -15.0,
    "Change%": "-0.98%"
  },
  {
    "Date": "2025-11-17",
    "Volume": 2681,
    "Close": 1530,
    "Change": NaN,
    "Change%": NaN
  },
  {
    "Date": "2025-11-14",
    "Volume": 3006,
    "Close": 1530,
    "Change": -80.0,
    "Change%": "-4.97%"
  },
  {
    "Date": "2025-11-13",
    "Volume": 10196,
    "Close": 1610,
    "Change": -50.0,
    "Change%": "-3.01%"
  },
  {
    "Date": "2025-11-12",
    "Volume": 14708,
    "Close": 1660,
    "Change": NaN,
    "Change%": NaN
  }
]