[
  {
    "Growth & Valuation": "Earnings Per Share",
    "Growth & Valuation.1": "358.83"
  },
  {
    "Growth & Valuation": "Price/Earning Ratio",
    "Growth & Valuation.1": "10.59"
  },
  {
    "Growth & Valuation": "Dividend Per Share",
    "Growth & Valuation.1": "275.50"
  },
  {
    "Growth & Valuation": "Dividend Yield",
    "Growth & Valuation.1": "7.25%"
  },
  {
    "Growth & Valuation": "Shares Outstanding",
    "Growth & Valuation.1": "20M"
  },
  {
    "Growth & Valuation": "Market Capitalization",
    "Growth & Valuation.1": "76B"
  }
]