[
  {
    "Date": "2025-11-06",
    "Volume": 508179,
    "Close": 12.02,
    "Change": -0.11,
    "Change%": "-0.91%"
  },
  {
    "Date": "2025-11-05",
    "Volume": 4725,
    "Close": 12.13,
    "Change": -0.1,
    "Change%": "-0.82%"
  },
  {
    "Date": "2025-11-04",
    "Volume": 160,
    "Close": 12.23,
    "Change": -0.09,
    "Change%": "-0.73%"
  },
  {
    "Date": "2025-11-03",
    "Volume": 256,
    "Close": 12.32,
    "Change": 0.03,
    "Change%": "+0.24%"
  },
  {
    "Date": "2025-10-31",
    "Volume": 125,
    "Close": 12.29,
    "Change": -0.07,
    "Change%": "-0.57%"
  },
  {
    "Date": "2025-10-30",
    "Volume": 268,
    "Close": 12.36,
    "Change": 0.19,
    "Change%": "+1.56%"
  },
  {
    "Date": "2025-10-28",
    "Volume": 5066,
    "Close": 12.17,
    "Change": 0.26,
    "Change%": "+2.18%"
  },
  {
    "Date": "2025-10-24",
    "Volume": 250054,
    "Close": 11.91,
    "Change": -0.09,
    "Change%": "-0.75%"
  },
  {
    "Date": "2025-10-21",
    "Volume": 1,
    "Close": 12.0,
    "Change": 0.22,
    "Change%": "+1.87%"
  },
  {
    "Date": "2025-10-20",
    "Volume": 1392,
    "Close": 11.78,
    "Change": NaN,
    "Change%": NaN
  }
]