[
  {
    "Date": "2025-11-07",
    "Volume": 294233,
    "Close": 88.04,
    "Change": -0.88,
    "Change%": "-0.99%"
  },
  {
    "Date": "2025-11-06",
    "Volume": 53800,
    "Close": 88.92,
    "Change": -0.34,
    "Change%": "-0.38%"
  },
  {
    "Date": "2025-11-05",
    "Volume": 139676,
    "Close": 89.26,
    "Change": 0.78,
    "Change%": "+0.88%"
  },
  {
    "Date": "2025-11-04",
    "Volume": 232698,
    "Close": 88.48,
    "Change": -0.71,
    "Change%": "-0.80%"
  },
  {
    "Date": "2025-11-03",
    "Volume": 76359,
    "Close": 89.19,
    "Change": -0.3,
    "Change%": "-0.34%"
  },
  {
    "Date": "2025-10-31",
    "Volume": 143490,
    "Close": 89.49,
    "Change": -0.27,
    "Change%": "-0.30%"
  },
  {
    "Date": "2025-10-30",
    "Volume": 178844,
    "Close": 89.76,
    "Change": 0.83,
    "Change%": "+0.93%"
  },
  {
    "Date": "2025-10-29",
    "Volume": 55571,
    "Close": 88.93,
    "Change": -0.56,
    "Change%": "-0.63%"
  },
  {
    "Date": "2025-10-28",
    "Volume": 243745,
    "Close": 89.49,
    "Change": 0.52,
    "Change%": "+0.58%"
  },
  {
    "Date": "2025-10-27",
    "Volume": 74613,
    "Close": 88.97,
    "Change": NaN,
    "Change%": NaN
  }
]