[
  {
    "Date": "2025-11-26",
    "Volume": 542,
    "Close": 41.72,
    "Change": -0.01,
    "Change%": "-0.02%"
  },
  {
    "Date": "2025-11-25",
    "Volume": 100,
    "Close": 41.73,
    "Change": NaN,
    "Change%": NaN
  },
  {
    "Date": "2025-11-21",
    "Volume": 16,
    "Close": 41.73,
    "Change": -0.27,
    "Change%": "-0.64%"
  },
  {
    "Date": "2025-11-18",
    "Volume": 2000,
    "Close": 42.0,
    "Change": -0.01,
    "Change%": "-0.02%"
  },
  {
    "Date": "2025-11-07",
    "Volume": 500,
    "Close": 42.01,
    "Change": 0.29,
    "Change%": "+0.70%"
  },
  {
    "Date": "2025-11-05",
    "Volume": 439,
    "Close": 41.72,
    "Change": 0.01,
    "Change%": "+0.02%"
  },
  {
    "Date": "2025-10-29",
    "Volume": 2000,
    "Close": 41.71,
    "Change": -0.01,
    "Change%": "-0.02%"
  },
  {
    "Date": "2025-10-28",
    "Volume": 21,
    "Close": 41.72,
    "Change": -2.77,
    "Change%": "-6.23%"
  },
  {
    "Date": "2025-10-21",
    "Volume": 1,
    "Close": 44.49,
    "Change": 2.49,
    "Change%": "+5.93%"
  },
  {
    "Date": "2025-10-15",
    "Volume": 230,
    "Close": 42.0,
    "Change": NaN,
    "Change%": NaN
  }
]