[
  {
    "Code": "WVR",
    "Name": "Weaver Fintech Ltd",
    "M. Cap.": "5.44B",
    "Close": 51.0,
    "YTD": "+70%"
  },
  {
    "Code": "SDO",
    "Name": "Stadio Holdings Limited",
    "M. Cap.": "9.27B",
    "Close": 10.9,
    "YTD": "+58%"
  },
  {
    "Code": "NCS",
    "Name": "Nictus Ltd",
    "M. Cap.": "98.9M",
    "Close": 1.85,
    "YTD": "+27.6%"
  },
  {
    "Code": "RTN",
    "Name": "Rex Trueform Group -N-",
    "M. Cap.": "254M",
    "Close": 12.51,
    "YTD": "+6.74%"
  },
  {
    "Code": "COH",
    "Name": "Curro Holdings Limited",
    "M. Cap.": "7.6B",
    "Close": 13.45,
    "YTD": "+3.07%"
  },
  {
    "Code": "ADH",
    "Name": "ADvTECH Ltd",
    "M. Cap.": "19.1B",
    "Close": 34.5,
    "YTD": "+1.95%"
  },
  {
    "Code": "TFGP",
    "Name": "Foschini Ltd 6.5% Preference Share",
    "M. Cap.": "202000",
    "Close": 1.01,
    "YTD": NaN
  },
  {
    "Code": "RTOP",
    "Name": "Rex Trueform Grp 6%Pref",
    "M. Cap.": "141400",
    "Close": 1.01,
    "YTD": NaN
  },
  {
    "Code": "LEW",
    "Name": "Lewis Group Ltd",
    "M. Cap.": "4.17B",
    "Close": 80.0,
    "YTD": "-0.11%"
  },
  {
    "Code": "RTO",
    "Name": "Rex Trueform Group Ltd",
    "M. Cap.": "42.2M",
    "Close": 11.21,
    "YTD": "-0.53%"
  }
]