[
  {
    "Date": "2025-11-27",
    "Volume": 30442,
    "Close": 14.2,
    "Change": 1.3,
    "Change%": "+10.08%"
  },
  {
    "Date": "2025-11-26",
    "Volume": 100,
    "Close": 12.9,
    "Change": -2.09,
    "Change%": "-13.94%"
  },
  {
    "Date": "2025-11-20",
    "Volume": 360,
    "Close": 14.99,
    "Change": 1.84,
    "Change%": "+13.99%"
  },
  {
    "Date": "2025-11-19",
    "Volume": 100,
    "Close": 13.15,
    "Change": -0.35,
    "Change%": "-2.59%"
  },
  {
    "Date": "2025-11-18",
    "Volume": 7938,
    "Close": 13.5,
    "Change": -2.0,
    "Change%": "-12.90%"
  },
  {
    "Date": "2025-11-17",
    "Volume": 79393,
    "Close": 15.5,
    "Change": -0.5,
    "Change%": "-3.12%"
  },
  {
    "Date": "2025-11-14",
    "Volume": 11548,
    "Close": 16.0,
    "Change": 1.5,
    "Change%": "+10.34%"
  },
  {
    "Date": "2025-11-13",
    "Volume": 9626,
    "Close": 14.5,
    "Change": 1.2,
    "Change%": "+9.02%"
  },
  {
    "Date": "2025-11-12",
    "Volume": 52370,
    "Close": 13.3,
    "Change": 0.35,
    "Change%": "+2.70%"
  },
  {
    "Date": "2025-11-11",
    "Volume": 30014,
    "Close": 12.95,
    "Change": NaN,
    "Change%": NaN
  }
]