[
  {
    "Growth & Valuation": "Earnings Per Share",
    "Growth & Valuation.1": "6.3510"
  },
  {
    "Growth & Valuation": "Price/Earning Ratio",
    "Growth & Valuation.1": "7.83"
  },
  {
    "Growth & Valuation": "Dividend Per Share",
    "Growth & Valuation.1": "4.28"
  },
  {
    "Growth & Valuation": "Dividend Yield",
    "Growth & Valuation.1": "8.61%"
  },
  {
    "Growth & Valuation": "Shares Outstanding",
    "Growth & Valuation.1": "387M"
  },
  {
    "Growth & Valuation": "Market Capitalization",
    "Growth & Valuation.1": "19.2B"
  }
]