[
  {
    "Date": "2025-11-04",
    "Volume": 418349,
    "Close": 6.31,
    "Change": -0.13,
    "Change%": "-2.02%"
  },
  {
    "Date": "2025-11-03",
    "Volume": 3705543,
    "Close": 6.44,
    "Change": 0.16,
    "Change%": "+2.55%"
  },
  {
    "Date": "2025-10-31",
    "Volume": 29395,
    "Close": 6.28,
    "Change": 0.08,
    "Change%": "+1.29%"
  },
  {
    "Date": "2025-10-30",
    "Volume": 160233,
    "Close": 6.2,
    "Change": 0.05,
    "Change%": "+0.81%"
  },
  {
    "Date": "2025-10-29",
    "Volume": 142882,
    "Close": 6.15,
    "Change": 0.15,
    "Change%": "+2.50%"
  },
  {
    "Date": "2025-10-28",
    "Volume": 2315230,
    "Close": 6.0,
    "Change": 0.12,
    "Change%": "+2.04%"
  },
  {
    "Date": "2025-10-27",
    "Volume": 14391,
    "Close": 5.88,
    "Change": -0.02,
    "Change%": "-0.34%"
  },
  {
    "Date": "2025-10-24",
    "Volume": 91370,
    "Close": 5.9,
    "Change": 0.08,
    "Change%": "+1.37%"
  },
  {
    "Date": "2025-10-23",
    "Volume": 110992,
    "Close": 5.82,
    "Change": 0.03,
    "Change%": "+0.52%"
  },
  {
    "Date": "2025-10-22",
    "Volume": 988204,
    "Close": 5.79,
    "Change": NaN,
    "Change%": NaN
  }
]