[
  {
    "Date": "2025-11-26",
    "Volume": 6963,
    "Close": 126.0,
    "Change": -2.0,
    "Change%": "-1.56%"
  },
  {
    "Date": "2025-11-25",
    "Volume": 4921,
    "Close": 128.0,
    "Change": 2.89,
    "Change%": "+2.31%"
  },
  {
    "Date": "2025-11-24",
    "Volume": 29484,
    "Close": 125.11,
    "Change": -3.88,
    "Change%": "-3.01%"
  },
  {
    "Date": "2025-11-21",
    "Volume": 6,
    "Close": 128.99,
    "Change": NaN,
    "Change%": NaN
  },
  {
    "Date": "2025-11-20",
    "Volume": 13325,
    "Close": 128.99,
    "Change": -0.96,
    "Change%": "-0.74%"
  },
  {
    "Date": "2025-11-19",
    "Volume": 1006,
    "Close": 129.95,
    "Change": -0.01,
    "Change%": "-0.01%"
  },
  {
    "Date": "2025-11-18",
    "Volume": 828,
    "Close": 129.96,
    "Change": 1.93,
    "Change%": "+1.51%"
  },
  {
    "Date": "2025-11-17",
    "Volume": 357,
    "Close": 128.03,
    "Change": -1.96,
    "Change%": "-1.51%"
  },
  {
    "Date": "2025-11-14",
    "Volume": 3945,
    "Close": 129.99,
    "Change": 4.99,
    "Change%": "+3.99%"
  },
  {
    "Date": "2025-11-13",
    "Volume": 3469,
    "Close": 125.0,
    "Change": NaN,
    "Change%": NaN
  }
]