[
  {
    "Date": "2025-11-03",
    "Volume": 1546,
    "Close": 46.36,
    "Change": -0.38,
    "Change%": "-0.81%"
  },
  {
    "Date": "2025-10-31",
    "Volume": 4916,
    "Close": 46.74,
    "Change": -0.02,
    "Change%": "-0.04%"
  },
  {
    "Date": "2025-10-30",
    "Volume": 1929,
    "Close": 46.76,
    "Change": 0.45,
    "Change%": "+0.97%"
  },
  {
    "Date": "2025-10-29",
    "Volume": 78830,
    "Close": 46.31,
    "Change": -0.93,
    "Change%": "-1.97%"
  },
  {
    "Date": "2025-10-28",
    "Volume": 7236,
    "Close": 47.24,
    "Change": -0.47,
    "Change%": "-0.99%"
  },
  {
    "Date": "2025-10-27",
    "Volume": 20603,
    "Close": 47.71,
    "Change": -0.06,
    "Change%": "-0.13%"
  },
  {
    "Date": "2025-10-24",
    "Volume": 29359,
    "Close": 47.77,
    "Change": 0.08,
    "Change%": "+0.17%"
  },
  {
    "Date": "2025-10-23",
    "Volume": 9745,
    "Close": 47.69,
    "Change": -0.12,
    "Change%": "-0.25%"
  },
  {
    "Date": "2025-10-22",
    "Volume": 4114,
    "Close": 47.81,
    "Change": -0.56,
    "Change%": "-1.16%"
  },
  {
    "Date": "2025-10-21",
    "Volume": 5742,
    "Close": 48.37,
    "Change": NaN,
    "Change%": NaN
  }
]