[
  {
    "Code": "IOC",
    "Name": "iOCO Ltd",
    "M. Cap.": "2.54B",
    "Close": 3.98,
    "YTD": "+62.5%"
  },
  {
    "Code": "DTC",
    "Name": "Datatec Ltd",
    "M. Cap.": "18.7B",
    "Close": 79.52,
    "YTD": "+59.5%"
  },
  {
    "Code": "PRX",
    "Name": "Prosus N.V.",
    "M. Cap.": "2.74T",
    "Close": 1152.49,
    "YTD": "+53.9%"
  },
  {
    "Code": "PBT",
    "Name": "PBT Holdings Ltd",
    "M. Cap.": "748M",
    "Close": 7.3,
    "YTD": "+30.4%"
  },
  {
    "Code": "AXX",
    "Name": "Araxi Ltd",
    "M. Cap.": "2.29B",
    "Close": 1.75,
    "YTD": "+14.4%"
  },
  {
    "Code": "AEL",
    "Name": "Altron: Allied Electronics Corporation",
    "M. Cap.": "7.76B",
    "Close": 18.78,
    "YTD": "-11.6%"
  },
  {
    "Code": "KRO",
    "Name": "Karooooo Ltd",
    "M. Cap.": "22.6B",
    "Close": 730.03,
    "YTD": "-16.1%"
  },
  {
    "Code": "BYI",
    "Name": "Bytes Technology Group Plc",
    "M. Cap.": "18.4B",
    "Close": 77.57,
    "YTD": "-21.1%"
  },
  {
    "Code": "LSK",
    "Name": "Lesaka Technologies",
    "M. Cap.": "5.6B",
    "Close": 66.5,
    "YTD": "-26.4%"
  },
  {
    "Code": "PWR",
    "Name": "PowerFleet Inc",
    "M. Cap.": "10.2B",
    "Close": 76.52,
    "YTD": "-42%"
  }
]