[
  {
    "Code": "NPK",
    "Name": "Nampak Ltd",
    "M. Cap.": "4.08B",
    "Close": 481.01,
    "YTD": "+15.6%"
  },
  {
    "Code": "BAW",
    "Name": "Barloworld Ltd",
    "M. Cap.": "22.6B",
    "Close": 119.3,
    "YTD": "+9.92%"
  },
  {
    "Code": "BAWP",
    "Name": "Barworld Ltd 6%Pref",
    "M. Cap.": "330000",
    "Close": 0.88,
    "YTD": "+8.64%"
  },
  {
    "Code": "BCF",
    "Name": "Bowler Metcalf Ltd",
    "M. Cap.": "1.04B",
    "Close": 13.9,
    "YTD": "+2.06%"
  },
  {
    "Code": "NPKP",
    "Name": "Nampak Ltd 6%Pref",
    "M. Cap.": "280000",
    "Close": 0.7,
    "YTD": NaN
  },
  {
    "Code": "NPP1",
    "Name": "Nampak Ltd 6,5%Pref",
    "M. Cap.": "131000",
    "Close": 1.31,
    "YTD": NaN
  },
  {
    "Code": "TPC",
    "Name": "Transpaco Ltd",
    "M. Cap.": "949M",
    "Close": 34.1,
    "YTD": "-9.04%"
  },
  {
    "Code": "BVT",
    "Name": "Bidvest Ltd",
    "M. Cap.": "76.6B",
    "Close": 224.98,
    "YTD": "-14.7%"
  },
  {
    "Code": "MPT",
    "Name": "Mpact Limited",
    "M. Cap.": "3.5B",
    "Close": 23.42,
    "YTD": "-20.7%"
  },
  {
    "Code": "ENX",
    "Name": "enX Group LImited",
    "M. Cap.": "784M",
    "Close": 4.3,
    "YTD": "-21.8%"
  }
]