[
  {
    "Date": "2025-11-03",
    "Volume": 200000,
    "Close": 0.59,
    "Change": NaN,
    "Change%": NaN
  },
  {
    "Date": "2025-10-31",
    "Volume": 89977,
    "Close": 0.59,
    "Change": NaN,
    "Change%": NaN
  },
  {
    "Date": "2025-10-30",
    "Volume": 29000,
    "Close": 0.59,
    "Change": NaN,
    "Change%": NaN
  },
  {
    "Date": "2025-10-29",
    "Volume": 97002,
    "Close": 0.59,
    "Change": NaN,
    "Change%": NaN
  },
  {
    "Date": "2025-10-28",
    "Volume": 286279,
    "Close": 0.59,
    "Change": -0.02,
    "Change%": "-3.28%"
  },
  {
    "Date": "2025-10-27",
    "Volume": 287200,
    "Close": 0.61,
    "Change": NaN,
    "Change%": NaN
  },
  {
    "Date": "2025-10-24",
    "Volume": 335993,
    "Close": 0.61,
    "Change": 0.01,
    "Change%": "+1.67%"
  },
  {
    "Date": "2025-10-23",
    "Volume": 373779,
    "Close": 0.6,
    "Change": -0.04,
    "Change%": "-6.25%"
  },
  {
    "Date": "2025-10-22",
    "Volume": 264179,
    "Close": 0.64,
    "Change": 0.04,
    "Change%": "+6.67%"
  },
  {
    "Date": "2025-10-21",
    "Volume": 342945,
    "Close": 0.6,
    "Change": NaN,
    "Change%": NaN
  }
]