[
  {
    "Growth & Valuation": "Earnings Per Share",
    "Growth & Valuation.1": "7.36"
  },
  {
    "Growth & Valuation": "Price/Earning Ratio",
    "Growth & Valuation.1": "10.38"
  },
  {
    "Growth & Valuation": "Dividend Per Share",
    "Growth & Valuation.1": "4.00"
  },
  {
    "Growth & Valuation": "Dividend Yield",
    "Growth & Valuation.1": "5.23%"
  },
  {
    "Growth & Valuation": "Shares Outstanding",
    "Growth & Valuation.1": "162M"
  },
  {
    "Growth & Valuation": "Market Capitalization",
    "Growth & Valuation.1": "12.4B"
  }
]