[
  {
    "Date": "2025-11-10",
    "Volume": 6854939,
    "Close": 26.75,
    "Change": 0.39,
    "Change%": "+1.48%"
  },
  {
    "Date": "2025-11-07",
    "Volume": 7774878,
    "Close": 26.36,
    "Change": -0.63,
    "Change%": "-2.33%"
  },
  {
    "Date": "2025-11-06",
    "Volume": 17902700,
    "Close": 26.99,
    "Change": 0.2,
    "Change%": "+0.75%"
  },
  {
    "Date": "2025-11-05",
    "Volume": 27509084,
    "Close": 26.79,
    "Change": NaN,
    "Change%": NaN
  },
  {
    "Date": "2025-11-04",
    "Volume": 13237551,
    "Close": 26.79,
    "Change": -0.52,
    "Change%": "-1.90%"
  },
  {
    "Date": "2025-11-03",
    "Volume": 17728006,
    "Close": 27.31,
    "Change": 0.91,
    "Change%": "+3.45%"
  },
  {
    "Date": "2025-10-31",
    "Volume": 13643843,
    "Close": 26.4,
    "Change": -0.17,
    "Change%": "-0.64%"
  },
  {
    "Date": "2025-10-30",
    "Volume": 11441098,
    "Close": 26.57,
    "Change": -0.24,
    "Change%": "-0.90%"
  },
  {
    "Date": "2025-10-29",
    "Volume": 14687298,
    "Close": 26.81,
    "Change": -0.01,
    "Change%": "-0.04%"
  },
  {
    "Date": "2025-10-28",
    "Volume": 13469831,
    "Close": 26.82,
    "Change": NaN,
    "Change%": NaN
  }
]