[
  {
    "Date": "2025-11-03",
    "Volume": 14,
    "Close": 81.52,
    "Change": 0.5,
    "Change%": "+0.62%"
  },
  {
    "Date": "2025-10-31",
    "Volume": 319,
    "Close": 81.02,
    "Change": -10.62,
    "Change%": "-11.59%"
  },
  {
    "Date": "2025-10-28",
    "Volume": 30,
    "Close": 91.64,
    "Change": -0.19,
    "Change%": "-0.21%"
  },
  {
    "Date": "2025-10-23",
    "Volume": 600,
    "Close": 91.83,
    "Change": -6.04,
    "Change%": "-6.17%"
  },
  {
    "Date": "2025-10-17",
    "Volume": 1200,
    "Close": 97.87,
    "Change": 1.71,
    "Change%": "+1.78%"
  },
  {
    "Date": "2025-10-16",
    "Volume": 2641,
    "Close": 96.16,
    "Change": 6.3,
    "Change%": "+7.01%"
  },
  {
    "Date": "2025-10-15",
    "Volume": 74,
    "Close": 89.86,
    "Change": 0.45,
    "Change%": "+0.50%"
  },
  {
    "Date": "2025-10-14",
    "Volume": 441,
    "Close": 89.41,
    "Change": 2.5,
    "Change%": "+2.88%"
  },
  {
    "Date": "2025-10-13",
    "Volume": 1200,
    "Close": 86.91,
    "Change": -2.05,
    "Change%": "-2.30%"
  },
  {
    "Date": "2025-10-08",
    "Volume": 1000,
    "Close": 88.96,
    "Change": NaN,
    "Change%": NaN
  }
]