[
  {
    "Code": "CHP",
    "Name": "Choppies Enterprises Limited",
    "M. Cap.": "5.66B",
    "Close": 3.1,
    "YTD": "+288%"
  },
  {
    "Code": "BOX",
    "Name": "Boxer Retail Ltd",
    "M. Cap.": "34.7B",
    "Close": 75.9,
    "YTD": "+17.9%"
  },
  {
    "Code": "BID",
    "Name": "BID Corporation Ltd",
    "M. Cap.": "143B",
    "Close": 423.78,
    "YTD": "-1.58%"
  },
  {
    "Code": "DCP",
    "Name": "Dis-Chem Pharmacies Limited",
    "M. Cap.": "30.5B",
    "Close": 35.42,
    "YTD": "-1.88%"
  },
  {
    "Code": "CLS",
    "Name": "Clicks Group Ltd",
    "M. Cap.": "84.9B",
    "Close": 362.26,
    "YTD": "-2.91%"
  },
  {
    "Code": "PIK",
    "Name": "Pick n Pay Stores Ltd",
    "M. Cap.": "20.3B",
    "Close": 27.24,
    "YTD": "-11.3%"
  },
  {
    "Code": "SPP",
    "Name": "The Spar Group Ltd",
    "M. Cap.": "20.9B",
    "Close": 108.73,
    "YTD": "-25.6%"
  },
  {
    "Code": "WVR",
    "Name": "Weaver Fintech Ltd",
    "M. Cap.": "5.66B",
    "Close": 53.0,
    "YTD": "+76.7%"
  },
  {
    "Code": "SDO",
    "Name": "Stadio Holdings Limited",
    "M. Cap.": "9.61B",
    "Close": 11.29,
    "YTD": "+63.6%"
  },
  {
    "Code": "NCS",
    "Name": "Nictus Ltd",
    "M. Cap.": "106M",
    "Close": 1.98,
    "YTD": "+36.6%"
  }
]