[
  {
    "Growth & Valuation": "Earnings Per Share",
    "Growth & Valuation.1": "2.3980"
  },
  {
    "Growth & Valuation": "Price/Earning Ratio",
    "Growth & Valuation.1": "7.63"
  },
  {
    "Growth & Valuation": "Dividend Per Share",
    "Growth & Valuation.1": NaN
  },
  {
    "Growth & Valuation": "Dividend Yield",
    "Growth & Valuation.1": NaN
  },
  {
    "Growth & Valuation": "Shares Outstanding",
    "Growth & Valuation.1": "339M"
  },
  {
    "Growth & Valuation": "Market Capitalization",
    "Growth & Valuation.1": "6.2B"
  }
]