[
  {
    "Date": "2025-11-13",
    "Volume": 1105,
    "Close": 56.79,
    "Change": -0.34,
    "Change%": "-0.60%"
  },
  {
    "Date": "2025-11-12",
    "Volume": 5238,
    "Close": 57.13,
    "Change": 0.05,
    "Change%": "+0.09%"
  },
  {
    "Date": "2025-11-11",
    "Volume": 19047,
    "Close": 57.08,
    "Change": 0.03,
    "Change%": "+0.05%"
  },
  {
    "Date": "2025-11-10",
    "Volume": 5973,
    "Close": 57.05,
    "Change": 0.33,
    "Change%": "+0.58%"
  },
  {
    "Date": "2025-11-07",
    "Volume": 4570,
    "Close": 56.72,
    "Change": -0.73,
    "Change%": "-1.27%"
  },
  {
    "Date": "2025-11-06",
    "Volume": 217,
    "Close": 57.45,
    "Change": -0.05,
    "Change%": "-0.09%"
  },
  {
    "Date": "2025-11-05",
    "Volume": 16314,
    "Close": 57.5,
    "Change": -0.16,
    "Change%": "-0.28%"
  },
  {
    "Date": "2025-11-04",
    "Volume": 6141,
    "Close": 57.66,
    "Change": 0.11,
    "Change%": "+0.19%"
  },
  {
    "Date": "2025-11-03",
    "Volume": 7597,
    "Close": 57.55,
    "Change": -0.25,
    "Change%": "-0.43%"
  },
  {
    "Date": "2025-10-31",
    "Volume": 5743,
    "Close": 57.8,
    "Change": NaN,
    "Change%": NaN
  }
]