[
  {
    "Growth & Valuation": "Earnings Per Share",
    "Growth & Valuation.1": "-0.2110"
  },
  {
    "Growth & Valuation": "Price/Earning Ratio",
    "Growth & Valuation.1": "-5.45"
  },
  {
    "Growth & Valuation": "Dividend Per Share",
    "Growth & Valuation.1": "1.33"
  },
  {
    "Growth & Valuation": "Dividend Yield",
    "Growth & Valuation.1": "116%"
  },
  {
    "Growth & Valuation": "Shares Outstanding",
    "Growth & Valuation.1": "223M"
  },
  {
    "Growth & Valuation": "Market Capitalization",
    "Growth & Valuation.1": "256M"
  }
]