[
  {
    "Date": "2025-11-14",
    "Volume": 1844403,
    "Close": 23.6,
    "Change": -0.05,
    "Change%": "-0.21%"
  },
  {
    "Date": "2025-11-13",
    "Volume": 2673079,
    "Close": 23.65,
    "Change": 0.05,
    "Change%": "+0.21%"
  },
  {
    "Date": "2025-11-12",
    "Volume": 1084067,
    "Close": 23.6,
    "Change": 0.5,
    "Change%": "+2.16%"
  },
  {
    "Date": "2025-11-11",
    "Volume": 3028329,
    "Close": 23.1,
    "Change": -0.42,
    "Change%": "-1.79%"
  },
  {
    "Date": "2025-11-10",
    "Volume": 2436804,
    "Close": 23.52,
    "Change": 0.47,
    "Change%": "+2.04%"
  },
  {
    "Date": "2025-11-07",
    "Volume": 592067,
    "Close": 23.05,
    "Change": -0.08,
    "Change%": "-0.35%"
  },
  {
    "Date": "2025-11-06",
    "Volume": 767208,
    "Close": 23.13,
    "Change": 0.18,
    "Change%": "+0.78%"
  },
  {
    "Date": "2025-11-05",
    "Volume": 2924929,
    "Close": 22.95,
    "Change": 0.18,
    "Change%": "+0.79%"
  },
  {
    "Date": "2025-11-04",
    "Volume": 898912,
    "Close": 22.77,
    "Change": 0.02,
    "Change%": "+0.09%"
  },
  {
    "Date": "2025-11-03",
    "Volume": 1032011,
    "Close": 22.75,
    "Change": NaN,
    "Change%": NaN
  }
]